[{"type":"sourcecred/weightedGraph","version":"0.1.0"},{"graphJSON":[{"type":"sourcecred/graph","version":"0.8.0"},{"edges":[{"address":["sourcecred","github","AUTHORS","5","sourcecred","github","USERLIKE","BOT","dependabot","4","sourcecred","github","COMMIT","MDY6Q29tbWl0MjcxODg3MzcwOjM4MTBlZjFjZjM0YTEwMWUxNzAzMjhiMDlkNDU5OWVmMGIyMWQwNmM="],"dstIndex":94,"srcIndex":165,"timestampMs":1596340264000},{"address":["sourcecred","github","AUTHORS","5","sourcecred","github","USERLIKE","BOT","dependabot","4","sourcecred","github","COMMIT","MDY6Q29tbWl0MjcxODg3MzcwOjc4Njg5ZDRjNzg3NTg0NDE0ZGE3NjFjNjM2YWU4NzU5NDAwMDE3Nzc="],"dstIndex":117,"srcIndex":165,"timestampMs":1596846528000},{"address":["sourcecred","github","AUTHORS","5","sourcecred","github","USERLIKE","BOT","dependabot","4","sourcecred","github","COMMIT","MDY6Q29tbWl0MjcxODg3MzcwOmJhYWQ2NWVhMDZhNjA1MWFiMDkwM2NmNzcxMzIzNTFhMWNhN2YwOTM="],"dstIndex":138,"srcIndex":165,"timestampMs":1595303914000},{"address":["sourcecred","github","AUTHORS","5","sourcecred","github","USERLIKE","BOT","dependabot","6","sourcecred","github","PULL","SecretFoundation","SecretWiki","1"],"dstIndex":157,"srcIndex":165,"timestampMs":1595303916000},{"address":["sourcecred","github","AUTHORS","5","sourcecred","github","USERLIKE","BOT","dependabot","6","sourcecred","github","PULL","SecretFoundation","SecretWiki","3"],"dstIndex":159,"srcIndex":165,"timestampMs":1596340266000},{"address":["sourcecred","github","AUTHORS","5","sourcecred","github","USERLIKE","BOT","dependabot","6","sourcecred","github","PULL","SecretFoundation","SecretWiki","4"],"dstIndex":160,"srcIndex":165,"timestampMs":1596846530000},{"address":["sourcecred","github","AUTHORS","5","sourcecred","github","USERLIKE","USER","jlwaugh","4","sourcecred","github","COMMIT","MDY6Q29tbWl0MjcxODg3MzcwOjA3YmM4MDBiMTU5MzkzNWQ1NzYyZGQ1ZDQ4OWIyYzMwY2Q2NTAyM2U="],"dstIndex":82,"srcIndex":166,"timestampMs":1595519141000},{"address":["sourcecred","github","AUTHORS","5","sourcecred","github","USERLIKE","USER","jlwaugh","4","sourcecred","github","COMMIT","MDY6Q29tbWl0MjcxODg3MzcwOjFmZDhkY2IxNjUzMjJlNTgxNmUyZTVjYzViYWNhNDFhMWM3OTdmMjU="],"dstIndex":89,"srcIndex":166,"timestampMs":1592440618000},{"address":["sourcecred","github","AUTHORS","5","sourcecred","github","USERLIKE","USER","jlwaugh","4","sourcecred","github","COMMIT","MDY6Q29tbWl0MjcxODg3MzcwOjQ5OTkwZmVhMTI3NzAxNzc2OTQ3OTMwYTc1MzRiM2FkYWUwZmM4ZTY="],"dstIndex":99,"srcIndex":166,"timestampMs":1598536432000},{"address":["sourcecred","github","AUTHORS","5","sourcecred","github","USERLIKE","USER","jlwaugh","4","sourcecred","github","COMMIT","MDY6Q29tbWl0MjcxODg3MzcwOjQyMzQ1ODQ5NTZlMWU0NTUyYjM2ZmVkN2U3MzU1YTQzYzAzYmRmYWU="],"dstIndex":101,"srcIndex":166,"timestampMs":1598482674000},{"address":["sourcecred","github","AUTHORS","5","sourcecred","github","USERLIKE","USER","jlwaugh","4","sourcecred","github","COMMIT","MDY6Q29tbWl0MjcxODg3MzcwOjU1MzZhNDZkYTZhOGU2OGFlZWZlMDkyNDkyZTYyY2U1NzY1ZTQyODk="],"dstIndex":103,"srcIndex":166,"timestampMs":1595944822000},{"address":["sourcecred","github","AUTHORS","5","sourcecred","github","USERLIKE","USER","jlwaugh","4","sourcecred","github","COMMIT","MDY6Q29tbWl0MjcxODg3MzcwOjVkNzVhZjYzZjk3YTk2MjQwOTVhMmE1MDhkMTUyZDNiZDlmMjk0ODc="],"dstIndex":107,"srcIndex":166,"timestampMs":1593614308000},{"address":["sourcecred","github","AUTHORS","5","sourcecred","github","USERLIKE","USER","jlwaugh","4","sourcecred","github","COMMIT","MDY6Q29tbWl0MjcxODg3MzcwOjY0NTJiMWM5Y2QxMzJmZTViNjBjNWJkOWE2ZDhmZTgxYmYwNzU4MDg="],"dstIndex":109,"srcIndex":166,"timestampMs":1598845968000},{"address":["sourcecred","github","AUTHORS","5","sourcecred","github","USERLIKE","USER","jlwaugh","4","sourcecred","github","COMMIT","MDY6Q29tbWl0MjcxODg3MzcwOjYxMDg1Y2I2NTA4Zjc4NjU2NjJmM2FjYzM4MGU5ZDhkNGY5ZWE3ZGY="],"dstIndex":111,"srcIndex":166,"timestampMs":1592504883000},{"address":["sourcecred","github","AUTHORS","5","sourcecred","github","USERLIKE","USER","jlwaugh","4","sourcecred","github","COMMIT","MDY6Q29tbWl0MjcxODg3MzcwOjZjMmIwNzNjMjIzMjdmZmRmMWY1ZjU2YTk4YWY3M2FlNDZmNzFkNDM="],"dstIndex":113,"srcIndex":166,"timestampMs":1595387965000},{"address":["sourcecred","github","AUTHORS","5","sourcecred","github","USERLIKE","USER","jlwaugh","4","sourcecred","github","COMMIT","MDY6Q29tbWl0MjcxODg3MzcwOjZkNGUzMDI1MzM1MjA2NjM5MjE4OWQzMDZhNmJlMDhhY2NhZmY3NDE="],"dstIndex":114,"srcIndex":166,"timestampMs":1598845983000},{"address":["sourcecred","github","AUTHORS","5","sourcecred","github","USERLIKE","USER","jlwaugh","4","sourcecred","github","COMMIT","MDY6Q29tbWl0MjcxODg3MzcwOjhjOWIyNWRhMWFiNmY4Yzg4Y2NjOGEzYzcxYWZlZWIwZjhjYzVlYmQ="],"dstIndex":125,"srcIndex":166,"timestampMs":1592439836000},{"address":["sourcecred","github","AUTHORS","5","sourcecred","github","USERLIKE","USER","jlwaugh","4","sourcecred","github","COMMIT","MDY6Q29tbWl0MjcxODg3MzcwOjhkMzk2YzkzYWQ0OTgwNjM5NzkxYTk3NWJlMDBjMTdlYjJiYTY4NDU="],"dstIndex":126,"srcIndex":166,"timestampMs":1598844612000},{"address":["sourcecred","github","AUTHORS","5","sourcecred","github","USERLIKE","USER","jlwaugh","4","sourcecred","github","COMMIT","MDY6Q29tbWl0MjcxODg3MzcwOmI0OWE3MThkMmVmNzA3ODdkZDU1YjM4ZWUxZTE3MWNmZjk0OTkxZDY="],"dstIndex":133,"srcIndex":166,"timestampMs":1598480182000},{"address":["sourcecred","github","AUTHORS","5","sourcecred","github","USERLIKE","USER","jlwaugh","4","sourcecred","github","COMMIT","MDY6Q29tbWl0MjcxODg3MzcwOmI1MWZhZGQ5MjFiODcyNGE0OTBjOWQ1N2FmMjQ1ZTRlYzUwOTdjMzc="],"dstIndex":134,"srcIndex":166,"timestampMs":1592504952000},{"address":["sourcecred","github","AUTHORS","5","sourcecred","github","USERLIKE","USER","jlwaugh","4","sourcecred","github","COMMIT","MDY6Q29tbWl0MjcxODg3MzcwOmIyM2ZkMTE5MTBkMjg4YjYxNTM5NjVjYjQ1NzYzNTFjODgwNjI1ZjQ="],"dstIndex":136,"srcIndex":166,"timestampMs":1598896748000},{"address":["sourcecred","github","AUTHORS","5","sourcecred","github","USERLIKE","USER","jlwaugh","4","sourcecred","github","COMMIT","MDY6Q29tbWl0MjcxODg3MzcwOmIzMmRhNDg2ZjdmMGEwZmM1OWM2ODk2MjQ4ODA0NGIwZmFhNmZiNDA="],"dstIndex":137,"srcIndex":166,"timestampMs":1592440477000},{"address":["sourcecred","github","AUTHORS","5","sourcecred","github","USERLIKE","USER","jlwaugh","4","sourcecred","github","COMMIT","MDY6Q29tbWl0MjcxODg3MzcwOmQ2ZmI2YzE4NDg4ZTA2YzI1NTk4MDhjZGM3OTQ0YTBkOTMwMWNmMzk="],"dstIndex":142,"srcIndex":166,"timestampMs":1595519490000},{"address":["sourcecred","github","AUTHORS","5","sourcecred","github","USERLIKE","USER","jlwaugh","4","sourcecred","github","COMMIT","MDY6Q29tbWl0MjcxODg3MzcwOmZmNGIzZjFmMmEwYmI3N2ZjMjYyZWJjYWZiMWI2N2I4OGVjYjM5ODg="],"dstIndex":156,"srcIndex":166,"timestampMs":1593613895000},{"address":["sourcecred","github","AUTHORS","5","sourcecred","github","USERLIKE","USER","lauraweindorf","8","sourcecred","github","COMMENT","PULL","SecretFoundation","SecretWiki","6","691184387"],"dstIndex":80,"srcIndex":167,"timestampMs":1599840575000},{"address":["sourcecred","github","AUTHORS","5","sourcecred","github","USERLIKE","USER","mohammedpatla","4","sourcecred","github","COMMIT","MDY6Q29tbWl0MjcxODg3MzcwOjAxMGQ0ZWJhODk1ODk5ZDMwMjM3MjYwZmE4YmNkNjQ3NWYyYjg5OGQ="],"dstIndex":84,"srcIndex":168,"timestampMs":1598840215000},{"address":["sourcecred","github","AUTHORS","5","sourcecred","github","USERLIKE","USER","mohammedpatla","4","sourcecred","github","COMMIT","MDY6Q29tbWl0MjcxODg3MzcwOjBlOTZiYmY0OTY5NzM2OTRhNzE4NDlmMTZlNjYyOWVjNzk5MDczZmU="],"dstIndex":85,"srcIndex":168,"timestampMs":1598841523000},{"address":["sourcecred","github","AUTHORS","5","sourcecred","github","USERLIKE","USER","mohammedpatla","4","sourcecred","github","COMMIT","MDY6Q29tbWl0MjcxODg3MzcwOjI2YmIyYmNhMmRlMWE3MzlmY2JiMzlhOTMzOTA2NmNiZTIwODRmY2Y="],"dstIndex":91,"srcIndex":168,"timestampMs":1594950359000},{"address":["sourcecred","github","AUTHORS","5","sourcecred","github","USERLIKE","USER","mohammedpatla","4","sourcecred","github","COMMIT","MDY6Q29tbWl0MjcxODg3MzcwOjIyMjY5ODcxMDRiM2JmM2IwOTBhMWU1NDM2YjAwMDc0ZGVlOWQ2MGM="],"dstIndex":92,"srcIndex":168,"timestampMs":1598842388000},{"address":["sourcecred","github","AUTHORS","5","sourcecred","github","USERLIKE","USER","mohammedpatla","4","sourcecred","github","COMMIT","MDY6Q29tbWl0MjcxODg3MzcwOjNmNjE5MDViNzExNDVmNTRhOGEyNjI5MzA0ZTZhNDE1ODE2YTYyYjE="],"dstIndex":98,"srcIndex":168,"timestampMs":1595462947000},{"address":["sourcecred","github","AUTHORS","5","sourcecred","github","USERLIKE","USER","mohammedpatla","4","sourcecred","github","COMMIT","MDY6Q29tbWl0MjcxODg3MzcwOjcwNzI5ZTM2ODcxMDM4YTJlMzIwZTViYWMwMjg3YzNjNzRkMzE4ODc="],"dstIndex":119,"srcIndex":168,"timestampMs":1595463272000},{"address":["sourcecred","github","AUTHORS","5","sourcecred","github","USERLIKE","USER","mohammedpatla","4","sourcecred","github","COMMIT","MDY6Q29tbWl0MjcxODg3MzcwOjgxODA2OGE5NmM1MGFmNWM0YTc3NTk0ZjAwYzAxYmI0MTYwMGUzYTg="],"dstIndex":122,"srcIndex":168,"timestampMs":1595463249000},{"address":["sourcecred","github","AUTHORS","5","sourcecred","github","USERLIKE","USER","mohammedpatla","4","sourcecred","github","COMMIT","MDY6Q29tbWl0MjcxODg3MzcwOmFmMTdmNTdjMTMwODkzZDBkMzhhN2NmZmNlZTAxMjEzMjIwYmFiYmI="],"dstIndex":132,"srcIndex":168,"timestampMs":1595463066000},{"address":["sourcecred","github","AUTHORS","5","sourcecred","github","USERLIKE","USER","mohammedpatla","4","sourcecred","github","COMMIT","MDY6Q29tbWl0MjcxODg3MzcwOmI2YTJlNjY5ZWEyNWIzOTMwMTAxNmE2N2UzNmZhYzU4MDFlODgyM2I="],"dstIndex":135,"srcIndex":168,"timestampMs":1598842292000},{"address":["sourcecred","github","AUTHORS","5","sourcecred","github","USERLIKE","USER","mohammedpatla","4","sourcecred","github","COMMIT","MDY6Q29tbWl0MjcxODg3MzcwOmQ4NTZlN2YzYzZmYzBlOWJkZDk1MjRhYzI5Y2M3ZWE3MGY5Nzc5YWQ="],"dstIndex":143,"srcIndex":168,"timestampMs":1598840438000},{"address":["sourcecred","github","AUTHORS","5","sourcecred","github","USERLIKE","USER","mohammedpatla","4","sourcecred","github","COMMIT","MDY6Q29tbWl0MjcxODg3MzcwOmVhOGVjOGYxNDJmOTNjNjgxZDMxNzhkYzgyZjVjMzBkOGI3Mzg2OTI="],"dstIndex":150,"srcIndex":168,"timestampMs":1598841799000},{"address":["sourcecred","github","AUTHORS","5","sourcecred","github","USERLIKE","USER","mohammedpatla","4","sourcecred","github","COMMIT","MDY6Q29tbWl0MjcxODg3MzcwOmVkM2Q4NGRhZmQ3ZTkzNDEwY2E4YjI0OGQxN2FhMzRhMTkwOTdjMDA="],"dstIndex":153,"srcIndex":168,"timestampMs":1598840697000},{"address":["sourcecred","github","AUTHORS","5","sourcecred","github","USERLIKE","USER","mohammedpatla","6","sourcecred","github","PULL","SecretFoundation","SecretWiki","2"],"dstIndex":158,"srcIndex":168,"timestampMs":1595463452000},{"address":["sourcecred","github","AUTHORS","5","sourcecred","github","USERLIKE","USER","mohammedpatla","6","sourcecred","github","PULL","SecretFoundation","SecretWiki","5"],"dstIndex":161,"srcIndex":168,"timestampMs":1598840801000},{"address":["sourcecred","github","AUTHORS","5","sourcecred","github","USERLIKE","USER","mohammedpatla","8","sourcecred","github","COMMENT","PULL","SecretFoundation","SecretWiki","5","683523498"],"dstIndex":77,"srcIndex":168,"timestampMs":1598842521000},{"address":["sourcecred","github","AUTHORS","5","sourcecred","github","USERLIKE","USER","moonstash","4","sourcecred","github","COMMIT","MDY6Q29tbWl0MjcxODg3MzcwOjA0ZWU3ZmQ0MjU5ZTI1ZTgwNjQ2YzQwNzczYmVkMmZlNTVhYzEzMTY="],"dstIndex":81,"srcIndex":169,"timestampMs":1598842730000},{"address":["sourcecred","github","AUTHORS","5","sourcecred","github","USERLIKE","USER","moonstash","4","sourcecred","github","COMMIT","MDY6Q29tbWl0MjcxODg3MzcwOjE0YWJkM2NiYTYxMTc0OWY3Y2FmNGNlMThlNDNmMjJkNmJiNDNhODU="],"dstIndex":86,"srcIndex":169,"timestampMs":1592498548000},{"address":["sourcecred","github","AUTHORS","5","sourcecred","github","USERLIKE","USER","moonstash","4","sourcecred","github","COMMIT","MDY6Q29tbWl0MjcxODg3MzcwOjI0OTRiYjRmMmYyMzk4Y2JmYmE3MGRlZDZmY2Y3MWVhYzAzNmM3MTQ="],"dstIndex":90,"srcIndex":169,"timestampMs":1598844118000},{"address":["sourcecred","github","AUTHORS","5","sourcecred","github","USERLIKE","USER","moonstash","4","sourcecred","github","COMMIT","MDY6Q29tbWl0MjcxODg3MzcwOjM1MzYwYjY1NGExYjgxZmRmZDQ1MjQ1YTc0YzkyM2M4MWI0Njk2YzA="],"dstIndex":93,"srcIndex":169,"timestampMs":1598962848000},{"address":["sourcecred","github","AUTHORS","5","sourcecred","github","USERLIKE","USER","moonstash","4","sourcecred","github","COMMIT","MDY6Q29tbWl0MjcxODg3MzcwOjMxNWY1N2VmMTNiMzU4ZmNhMjRiYmZhZWJlNTBmZjgyNWM5ZjA5Y2U="],"dstIndex":95,"srcIndex":169,"timestampMs":1598904675000},{"address":["sourcecred","github","AUTHORS","5","sourcecred","github","USERLIKE","USER","moonstash","4","sourcecred","github","COMMIT","MDY6Q29tbWl0MjcxODg3MzcwOjQxZDBmZTczNjA2ZGI1NzRhNWZmNDA0NjkwNjg4MWYyMGY5YzIyOTc="],"dstIndex":100,"srcIndex":169,"timestampMs":1598963064000},{"address":["sourcecred","github","AUTHORS","5","sourcecred","github","USERLIKE","USER","moonstash","4","sourcecred","github","COMMIT","MDY6Q29tbWl0MjcxODg3MzcwOjUwNmQyMTFlN2FiOWU3ODRlODUyM2U4OTEwNzU0NjcyYjgwMGVlYjg="],"dstIndex":104,"srcIndex":169,"timestampMs":1594226903000},{"address":["sourcecred","github","AUTHORS","5","sourcecred","github","USERLIKE","USER","moonstash","4","sourcecred","github","COMMIT","MDY6Q29tbWl0MjcxODg3MzcwOjUxNTMwMmZlNGJmYzM3NDQxMTRiY2JiYjNlYzAzZjM0NGQyNDM0NTU="],"dstIndex":105,"srcIndex":169,"timestampMs":1598844890000},{"address":["sourcecred","github","AUTHORS","5","sourcecred","github","USERLIKE","USER","moonstash","4","sourcecred","github","COMMIT","MDY6Q29tbWl0MjcxODg3MzcwOjY1OGYyYjE0ZGEyNGFhMmJmYTkwM2UxMGQ4Y2UyYzhkZWU1ZjE4MmI="],"dstIndex":110,"srcIndex":169,"timestampMs":1598841804000},{"address":["sourcecred","github","AUTHORS","5","sourcecred","github","USERLIKE","USER","moonstash","4","sourcecred","github","COMMIT","MDY6Q29tbWl0MjcxODg3MzcwOjYxNjI0OTk3ZWY4ZDEwMGJhYjU4Y2JjMmRmMGUxYmJhYTVhNzhhMDI="],"dstIndex":112,"srcIndex":169,"timestampMs":1594225660000},{"address":["sourcecred","github","AUTHORS","5","sourcecred","github","USERLIKE","USER","moonstash","4","sourcecred","github","COMMIT","MDY6Q29tbWl0MjcxODg3MzcwOjc1OTliOWVkZWVkZjg2OTdhYmIwOGNiMWM0YzdhNGVkZmQ1YTE5NGU="],"dstIndex":116,"srcIndex":169,"timestampMs":1598844760000},{"address":["sourcecred","github","AUTHORS","5","sourcecred","github","USERLIKE","USER","moonstash","4","sourcecred","github","COMMIT","MDY6Q29tbWl0MjcxODg3MzcwOjc4YWU2NjFjMWZmNDJhZTlkYTA2ZThkNWNiMTBjZmYzOGQ3YjM2MGM="],"dstIndex":118,"srcIndex":169,"timestampMs":1598841044000},{"address":["sourcecred","github","AUTHORS","5","sourcecred","github","USERLIKE","USER","moonstash","4","sourcecred","github","COMMIT","MDY6Q29tbWl0MjcxODg3MzcwOjdiY2Y5ZTYyNTY4MDA2YjkxMzRmOTRjYmI2YWJhYWVkNzJlODI1ZWQ="],"dstIndex":121,"srcIndex":169,"timestampMs":1598841539000},{"address":["sourcecred","github","AUTHORS","5","sourcecred","github","USERLIKE","USER","moonstash","4","sourcecred","github","COMMIT","MDY6Q29tbWl0MjcxODg3MzcwOjhiY2MwMTZkMjgwNWY0OTBkMjZmMDJjMzZkMzVmNmZiNmYzNzcxMDE="],"dstIndex":124,"srcIndex":169,"timestampMs":1594232071000},{"address":["sourcecred","github","AUTHORS","5","sourcecred","github","USERLIKE","USER","moonstash","4","sourcecred","github","COMMIT","MDY6Q29tbWl0MjcxODg3MzcwOjhlODMzNWU0MDU1NjViY2VjOWI0NDhlZmNmMjEzOTcyOTczYTZmMmM="],"dstIndex":127,"srcIndex":169,"timestampMs":1598835204000},{"address":["sourcecred","github","AUTHORS","5","sourcecred","github","USERLIKE","USER","moonstash","4","sourcecred","github","COMMIT","MDY6Q29tbWl0MjcxODg3MzcwOjljYzI2MGNlZjg3NTY1ODY1MTMyOWVjMTcxMGZjMDY5N2ZmMzI2ZDk="],"dstIndex":130,"srcIndex":169,"timestampMs":1594225941000},{"address":["sourcecred","github","AUTHORS","5","sourcecred","github","USERLIKE","USER","moonstash","4","sourcecred","github","COMMIT","MDY6Q29tbWl0MjcxODg3MzcwOmE3OTZmNzExMDI2YTc1YzNhMzM3YWU4Njk2ZmUzZWU2MWNlNDdlMzg="],"dstIndex":131,"srcIndex":169,"timestampMs":1598845380000},{"address":["sourcecred","github","AUTHORS","5","sourcecred","github","USERLIKE","USER","moonstash","4","sourcecred","github","COMMIT","MDY6Q29tbWl0MjcxODg3MzcwOmNiNjZiNDU4NTU3ZDhhNGI2ZGRiYjIzOTE1NGU2OTMxYTEwNWU4M2E="],"dstIndex":140,"srcIndex":169,"timestampMs":1598836339000},{"address":["sourcecred","github","AUTHORS","5","sourcecred","github","USERLIKE","USER","moonstash","4","sourcecred","github","COMMIT","MDY6Q29tbWl0MjcxODg3MzcwOmQ1MWUyZjcyMTkzY2QzOTlhYzI4ZTJkMmI5Mzg5NGI2ZDc4NmY3OTM="],"dstIndex":141,"srcIndex":169,"timestampMs":1599616092000},{"address":["sourcecred","github","AUTHORS","5","sourcecred","github","USERLIKE","USER","moonstash","4","sourcecred","github","COMMIT","MDY6Q29tbWl0MjcxODg3MzcwOmU4NTk4YTBkYWY1MzFmZWY3ODhkNTQ5MWUxOTI4MTEzNGJjYTIxYzA="],"dstIndex":146,"srcIndex":169,"timestampMs":1598836209000},{"address":["sourcecred","github","AUTHORS","5","sourcecred","github","USERLIKE","USER","moonstash","4","sourcecred","github","COMMIT","MDY6Q29tbWl0MjcxODg3MzcwOmUyMWRmOTY5M2UxYjQyYjc5ZDExYjNjNGUwZGJjMjVkNzNhMTY4NDQ="],"dstIndex":147,"srcIndex":169,"timestampMs":1598836293000},{"address":["sourcecred","github","AUTHORS","5","sourcecred","github","USERLIKE","USER","moonstash","4","sourcecred","github","COMMIT","MDY6Q29tbWl0MjcxODg3MzcwOmUyYzk3NjgwZGE2NmI0YTU5OTZkNTI2MTExMjNjYjdmNjk1MDMyM2I="],"dstIndex":148,"srcIndex":169,"timestampMs":1598835325000},{"address":["sourcecred","github","AUTHORS","5","sourcecred","github","USERLIKE","USER","moonstash","4","sourcecred","github","COMMIT","MDY6Q29tbWl0MjcxODg3MzcwOmY0Mjk5MjBhZDc4Y2Q3Mjk4NWFiZmVmZjkxYzBkMjFjY2RmYjQ4MTY="],"dstIndex":154,"srcIndex":169,"timestampMs":1598836079000},{"address":["sourcecred","github","AUTHORS","5","sourcecred","github","USERLIKE","USER","moonstash","4","sourcecred","github","COMMIT","MDY6Q29tbWl0MjcxODg3MzcwOmZmN2ZiYTEwNDJiNDQ2ZWM0MzY5OGUwNDM4OWVkYjk4YmJkN2E2M2I="],"dstIndex":155,"srcIndex":169,"timestampMs":1598841108000},{"address":["sourcecred","github","AUTHORS","5","sourcecred","github","USERLIKE","USER","moonstash","8","sourcecred","github","COMMENT","PULL","SecretFoundation","SecretWiki","5","683518918"],"dstIndex":76,"srcIndex":169,"timestampMs":1598841205000},{"address":["sourcecred","github","AUTHORS","5","sourcecred","github","USERLIKE","USER","moonstash","8","sourcecred","github","COMMENT","PULL","SecretFoundation","SecretWiki","6","685292773"],"dstIndex":78,"srcIndex":169,"timestampMs":1599022000000},{"address":["sourcecred","github","AUTHORS","5","sourcecred","github","USERLIKE","USER","the-dusky","6","sourcecred","github","PULL","SecretFoundation","SecretWiki","6"],"dstIndex":162,"srcIndex":170,"timestampMs":1599013086000},{"address":["sourcecred","github","AUTHORS","5","sourcecred","github","USERLIKE","USER","the-dusky","6","sourcecred","github","PULL","SecretFoundation","SecretWiki","7"],"dstIndex":163,"srcIndex":170,"timestampMs":1599616004000},{"address":["sourcecred","github","AUTHORS","5","sourcecred","github","USERLIKE","USER","the-dusky","8","sourcecred","github","COMMENT","PULL","SecretFoundation","SecretWiki","6","689233361"],"dstIndex":79,"srcIndex":170,"timestampMs":1599613142000},{"address":["sourcecred","github","AUTHORS","5","sourcecred","github","USERLIKE","USER","torsecret","4","sourcecred","github","COMMIT","MDY6Q29tbWl0MjcxODg3MzcwOjA5YjhiNWQ3NTc5MTZkNGZiNzNkMmRhOWM3Y2I0ZTAxOTI1ODA1NmQ="],"dstIndex":83,"srcIndex":171,"timestampMs":1598358973000},{"address":["sourcecred","github","AUTHORS","5","sourcecred","github","USERLIKE","USER","torsecret","4","sourcecred","github","COMMIT","MDY6Q29tbWl0MjcxODg3MzcwOjE3NzBjMmI4MzI0Y2U4M2EzNzcxYzQ2NDRlZTIxYzE3ZjUzY2RhYjE="],"dstIndex":87,"srcIndex":171,"timestampMs":1593433030000},{"address":["sourcecred","github","AUTHORS","5","sourcecred","github","USERLIKE","USER","torsecret","4","sourcecred","github","COMMIT","MDY6Q29tbWl0MjcxODg3MzcwOjFlOWI4NTViMmI1NDEzZTg5YWFmYjAyYTdjNWQ4N2RkN2E5MTJkNjI="],"dstIndex":88,"srcIndex":171,"timestampMs":1593010444000},{"address":["sourcecred","github","AUTHORS","5","sourcecred","github","USERLIKE","USER","torsecret","4","sourcecred","github","COMMIT","MDY6Q29tbWl0MjcxODg3MzcwOjMxZWE1YTEwZGQyY2MwNzMxZDNhNjRlNzU1NDdkZmIwMzZiYjFkNzk="],"dstIndex":96,"srcIndex":171,"timestampMs":1598293405000},{"address":["sourcecred","github","AUTHORS","5","sourcecred","github","USERLIKE","USER","torsecret","4","sourcecred","github","COMMIT","MDY6Q29tbWl0MjcxODg3MzcwOjMzYWE4YzkyY2ZkYmM4MGE3NTZhYzlkMzcxY2U3Y2MxNzg1YmMyMjQ="],"dstIndex":97,"srcIndex":171,"timestampMs":1595697005000},{"address":["sourcecred","github","AUTHORS","5","sourcecred","github","USERLIKE","USER","torsecret","4","sourcecred","github","COMMIT","MDY6Q29tbWl0MjcxODg3MzcwOjRjZmRkMDRkY2FlN2IxYTRlMDA1NmFiYTBkZWJhZWQ4MDg2MDBhYjg="],"dstIndex":102,"srcIndex":171,"timestampMs":1598293530000},{"address":["sourcecred","github","AUTHORS","5","sourcecred","github","USERLIKE","USER","torsecret","4","sourcecred","github","COMMIT","MDY6Q29tbWl0MjcxODg3MzcwOjVkMzcxZTViNWE3NDlkMGZiZDhlNzk0OGZiZWYzOTJhMmU3YWQzZDA="],"dstIndex":106,"srcIndex":171,"timestampMs":1593518164000},{"address":["sourcecred","github","AUTHORS","5","sourcecred","github","USERLIKE","USER","torsecret","4","sourcecred","github","COMMIT","MDY6Q29tbWl0MjcxODg3MzcwOjY0MzU2NzQyZWRkZTk2ZWJhOGY0Y2I2YTY0YzY5NDZiYTM2YjY3MTA="],"dstIndex":108,"srcIndex":171,"timestampMs":1597675149000},{"address":["sourcecred","github","AUTHORS","5","sourcecred","github","USERLIKE","USER","torsecret","4","sourcecred","github","COMMIT","MDY6Q29tbWl0MjcxODg3MzcwOjZmY2NkMjYzYjhjMzU5YWI2NGYzNDNjYTI2YTYwNWJlNDRjOTBjM2E="],"dstIndex":115,"srcIndex":171,"timestampMs":1598463969000},{"address":["sourcecred","github","AUTHORS","5","sourcecred","github","USERLIKE","USER","torsecret","4","sourcecred","github","COMMIT","MDY6Q29tbWl0MjcxODg3MzcwOjczYjcwZWJiYTZmODIyMTg2ODI5OTgzMjI3MDE0OWIyNzg5NGQ4ODI="],"dstIndex":120,"srcIndex":171,"timestampMs":1593518225000},{"address":["sourcecred","github","AUTHORS","5","sourcecred","github","USERLIKE","USER","torsecret","4","sourcecred","github","COMMIT","MDY6Q29tbWl0MjcxODg3MzcwOjgzMDczMTZkYmRhOWE0YTI3NmFiOGJjZDM0NzZhZDk3NjJkNTBiMDc="],"dstIndex":123,"srcIndex":171,"timestampMs":1593433916000},{"address":["sourcecred","github","AUTHORS","5","sourcecred","github","USERLIKE","USER","torsecret","4","sourcecred","github","COMMIT","MDY6Q29tbWl0MjcxODg3MzcwOjkwMzIyMDY5Mjk4ZWNkZDE2ZGFjY2MxZTFiNWQyYjY1ODRjODViZjU="],"dstIndex":128,"srcIndex":171,"timestampMs":1593518052000},{"address":["sourcecred","github","AUTHORS","5","sourcecred","github","USERLIKE","USER","torsecret","4","sourcecred","github","COMMIT","MDY6Q29tbWl0MjcxODg3MzcwOjkxYWRlZTliMDk4YTg2N2MxYjY3OWJiM2UxYmFhMDkxNjg5ZjA3YWE="],"dstIndex":129,"srcIndex":171,"timestampMs":1593517954000},{"address":["sourcecred","github","AUTHORS","5","sourcecred","github","USERLIKE","USER","torsecret","4","sourcecred","github","COMMIT","MDY6Q29tbWl0MjcxODg3MzcwOmM2YmU2OTBmYmVmYzg5MjU0ODdhZjUxNDYzZDZkODhhOTBhNDAxZTY="],"dstIndex":139,"srcIndex":171,"timestampMs":1592838315000},{"address":["sourcecred","github","AUTHORS","5","sourcecred","github","USERLIKE","USER","torsecret","4","sourcecred","github","COMMIT","MDY6Q29tbWl0MjcxODg3MzcwOmQyNWVkMjQ0NWNkM2VmYjAwMGNiYjIyYTRhZjliMGY0NWIyY2E0OTI="],"dstIndex":144,"srcIndex":171,"timestampMs":1593468514000},{"address":["sourcecred","github","AUTHORS","5","sourcecred","github","USERLIKE","USER","torsecret","4","sourcecred","github","COMMIT","MDY6Q29tbWl0MjcxODg3MzcwOmRmZDZlMDM4OTBiNDdkYWYyZThiMWVkNDUwMzY3MjM0OWIwMDk1NTU="],"dstIndex":145,"srcIndex":171,"timestampMs":1593432420000},{"address":["sourcecred","github","AUTHORS","5","sourcecred","github","USERLIKE","USER","torsecret","4","sourcecred","github","COMMIT","MDY6Q29tbWl0MjcxODg3MzcwOmUzZDhjM2U1OTEzMGE0MjliZTA1MDVlY2U2YWExYmJlOTk4NDc4MjU="],"dstIndex":149,"srcIndex":171,"timestampMs":1593010586000},{"address":["sourcecred","github","AUTHORS","5","sourcecred","github","USERLIKE","USER","torsecret","4","sourcecred","github","COMMIT","MDY6Q29tbWl0MjcxODg3MzcwOmVhYWZlNDNkODgwODJhMTNhYWM4NzYyMWQ2YzViNjIwOTk4NDEzMDQ="],"dstIndex":151,"srcIndex":171,"timestampMs":1597694366000},{"address":["sourcecred","github","CORRESPONDS_TO_COMMIT_TYPE","4","sourcecred","github","COMMIT","MDY6Q29tbWl0MjcxODg3MzcwOjA0ZWU3ZmQ0MjU5ZTI1ZTgwNjQ2YzQwNzczYmVkMmZlNTVhYzEzMTY="],"dstIndex":1,"srcIndex":81,"timestampMs":1598842730000},{"address":["sourcecred","github","CORRESPONDS_TO_COMMIT_TYPE","4","sourcecred","github","COMMIT","MDY6Q29tbWl0MjcxODg3MzcwOjA3YmM4MDBiMTU5MzkzNWQ1NzYyZGQ1ZDQ4OWIyYzMwY2Q2NTAyM2U="],"dstIndex":2,"srcIndex":82,"timestampMs":1595519141000},{"address":["sourcecred","github","CORRESPONDS_TO_COMMIT_TYPE","4","sourcecred","github","COMMIT","MDY6Q29tbWl0MjcxODg3MzcwOjA5YjhiNWQ3NTc5MTZkNGZiNzNkMmRhOWM3Y2I0ZTAxOTI1ODA1NmQ="],"dstIndex":3,"srcIndex":83,"timestampMs":1598358973000},{"address":["sourcecred","github","CORRESPONDS_TO_COMMIT_TYPE","4","sourcecred","github","COMMIT","MDY6Q29tbWl0MjcxODg3MzcwOjAxMGQ0ZWJhODk1ODk5ZDMwMjM3MjYwZmE4YmNkNjQ3NWYyYjg5OGQ="],"dstIndex":0,"srcIndex":84,"timestampMs":1598840215000},{"address":["sourcecred","github","CORRESPONDS_TO_COMMIT_TYPE","4","sourcecred","github","COMMIT","MDY6Q29tbWl0MjcxODg3MzcwOjBlOTZiYmY0OTY5NzM2OTRhNzE4NDlmMTZlNjYyOWVjNzk5MDczZmU="],"dstIndex":4,"srcIndex":85,"timestampMs":1598841523000},{"address":["sourcecred","github","CORRESPONDS_TO_COMMIT_TYPE","4","sourcecred","github","COMMIT","MDY6Q29tbWl0MjcxODg3MzcwOjE0YWJkM2NiYTYxMTc0OWY3Y2FmNGNlMThlNDNmMjJkNmJiNDNhODU="],"dstIndex":5,"srcIndex":86,"timestampMs":1592498548000},{"address":["sourcecred","github","CORRESPONDS_TO_COMMIT_TYPE","4","sourcecred","github","COMMIT","MDY6Q29tbWl0MjcxODg3MzcwOjE3NzBjMmI4MzI0Y2U4M2EzNzcxYzQ2NDRlZTIxYzE3ZjUzY2RhYjE="],"dstIndex":6,"srcIndex":87,"timestampMs":1593433030000},{"address":["sourcecred","github","CORRESPONDS_TO_COMMIT_TYPE","4","sourcecred","github","COMMIT","MDY6Q29tbWl0MjcxODg3MzcwOjFlOWI4NTViMmI1NDEzZTg5YWFmYjAyYTdjNWQ4N2RkN2E5MTJkNjI="],"dstIndex":7,"srcIndex":88,"timestampMs":1593010444000},{"address":["sourcecred","github","CORRESPONDS_TO_COMMIT_TYPE","4","sourcecred","github","COMMIT","MDY6Q29tbWl0MjcxODg3MzcwOjFmZDhkY2IxNjUzMjJlNTgxNmUyZTVjYzViYWNhNDFhMWM3OTdmMjU="],"dstIndex":8,"srcIndex":89,"timestampMs":1592440618000},{"address":["sourcecred","github","CORRESPONDS_TO_COMMIT_TYPE","4","sourcecred","github","COMMIT","MDY6Q29tbWl0MjcxODg3MzcwOjI0OTRiYjRmMmYyMzk4Y2JmYmE3MGRlZDZmY2Y3MWVhYzAzNmM3MTQ="],"dstIndex":10,"srcIndex":90,"timestampMs":1598844118000},{"address":["sourcecred","github","CORRESPONDS_TO_COMMIT_TYPE","4","sourcecred","github","COMMIT","MDY6Q29tbWl0MjcxODg3MzcwOjI2YmIyYmNhMmRlMWE3MzlmY2JiMzlhOTMzOTA2NmNiZTIwODRmY2Y="],"dstIndex":11,"srcIndex":91,"timestampMs":1594950359000},{"address":["sourcecred","github","CORRESPONDS_TO_COMMIT_TYPE","4","sourcecred","github","COMMIT","MDY6Q29tbWl0MjcxODg3MzcwOjIyMjY5ODcxMDRiM2JmM2IwOTBhMWU1NDM2YjAwMDc0ZGVlOWQ2MGM="],"dstIndex":9,"srcIndex":92,"timestampMs":1598842388000},{"address":["sourcecred","github","CORRESPONDS_TO_COMMIT_TYPE","4","sourcecred","github","COMMIT","MDY6Q29tbWl0MjcxODg3MzcwOjM1MzYwYjY1NGExYjgxZmRmZDQ1MjQ1YTc0YzkyM2M4MWI0Njk2YzA="],"dstIndex":15,"srcIndex":93,"timestampMs":1598962848000},{"address":["sourcecred","github","CORRESPONDS_TO_COMMIT_TYPE","4","sourcecred","github","COMMIT","MDY6Q29tbWl0MjcxODg3MzcwOjM4MTBlZjFjZjM0YTEwMWUxNzAzMjhiMDlkNDU5OWVmMGIyMWQwNmM="],"dstIndex":16,"srcIndex":94,"timestampMs":1596340264000},{"address":["sourcecred","github","CORRESPONDS_TO_COMMIT_TYPE","4","sourcecred","github","COMMIT","MDY6Q29tbWl0MjcxODg3MzcwOjMxNWY1N2VmMTNiMzU4ZmNhMjRiYmZhZWJlNTBmZjgyNWM5ZjA5Y2U="],"dstIndex":12,"srcIndex":95,"timestampMs":1598904675000},{"address":["sourcecred","github","CORRESPONDS_TO_COMMIT_TYPE","4","sourcecred","github","COMMIT","MDY6Q29tbWl0MjcxODg3MzcwOjMxZWE1YTEwZGQyY2MwNzMxZDNhNjRlNzU1NDdkZmIwMzZiYjFkNzk="],"dstIndex":13,"srcIndex":96,"timestampMs":1598293405000},{"address":["sourcecred","github","CORRESPONDS_TO_COMMIT_TYPE","4","sourcecred","github","COMMIT","MDY6Q29tbWl0MjcxODg3MzcwOjMzYWE4YzkyY2ZkYmM4MGE3NTZhYzlkMzcxY2U3Y2MxNzg1YmMyMjQ="],"dstIndex":14,"srcIndex":97,"timestampMs":1595697005000},{"address":["sourcecred","github","CORRESPONDS_TO_COMMIT_TYPE","4","sourcecred","github","COMMIT","MDY6Q29tbWl0MjcxODg3MzcwOjNmNjE5MDViNzExNDVmNTRhOGEyNjI5MzA0ZTZhNDE1ODE2YTYyYjE="],"dstIndex":17,"srcIndex":98,"timestampMs":1595462947000},{"address":["sourcecred","github","CORRESPONDS_TO_COMMIT_TYPE","4","sourcecred","github","COMMIT","MDY6Q29tbWl0MjcxODg3MzcwOjQ5OTkwZmVhMTI3NzAxNzc2OTQ3OTMwYTc1MzRiM2FkYWUwZmM4ZTY="],"dstIndex":20,"srcIndex":99,"timestampMs":1598536432000},{"address":["sourcecred","github","CORRESPONDS_TO_COMMIT_TYPE","4","sourcecred","github","COMMIT","MDY6Q29tbWl0MjcxODg3MzcwOjQxZDBmZTczNjA2ZGI1NzRhNWZmNDA0NjkwNjg4MWYyMGY5YzIyOTc="],"dstIndex":18,"srcIndex":100,"timestampMs":1598963064000},{"address":["sourcecred","github","CORRESPONDS_TO_COMMIT_TYPE","4","sourcecred","github","COMMIT","MDY6Q29tbWl0MjcxODg3MzcwOjQyMzQ1ODQ5NTZlMWU0NTUyYjM2ZmVkN2U3MzU1YTQzYzAzYmRmYWU="],"dstIndex":19,"srcIndex":101,"timestampMs":1598482674000},{"address":["sourcecred","github","CORRESPONDS_TO_COMMIT_TYPE","4","sourcecred","github","COMMIT","MDY6Q29tbWl0MjcxODg3MzcwOjRjZmRkMDRkY2FlN2IxYTRlMDA1NmFiYTBkZWJhZWQ4MDg2MDBhYjg="],"dstIndex":21,"srcIndex":102,"timestampMs":1598293530000},{"address":["sourcecred","github","CORRESPONDS_TO_COMMIT_TYPE","4","sourcecred","github","COMMIT","MDY6Q29tbWl0MjcxODg3MzcwOjU1MzZhNDZkYTZhOGU2OGFlZWZlMDkyNDkyZTYyY2U1NzY1ZTQyODk="],"dstIndex":24,"srcIndex":103,"timestampMs":1595944822000},{"address":["sourcecred","github","CORRESPONDS_TO_COMMIT_TYPE","4","sourcecred","github","COMMIT","MDY6Q29tbWl0MjcxODg3MzcwOjUwNmQyMTFlN2FiOWU3ODRlODUyM2U4OTEwNzU0NjcyYjgwMGVlYjg="],"dstIndex":22,"srcIndex":104,"timestampMs":1594226903000},{"address":["sourcecred","github","CORRESPONDS_TO_COMMIT_TYPE","4","sourcecred","github","COMMIT","MDY6Q29tbWl0MjcxODg3MzcwOjUxNTMwMmZlNGJmYzM3NDQxMTRiY2JiYjNlYzAzZjM0NGQyNDM0NTU="],"dstIndex":23,"srcIndex":105,"timestampMs":1598844890000},{"address":["sourcecred","github","CORRESPONDS_TO_COMMIT_TYPE","4","sourcecred","github","COMMIT","MDY6Q29tbWl0MjcxODg3MzcwOjVkMzcxZTViNWE3NDlkMGZiZDhlNzk0OGZiZWYzOTJhMmU3YWQzZDA="],"dstIndex":25,"srcIndex":106,"timestampMs":1593518164000},{"address":["sourcecred","github","CORRESPONDS_TO_COMMIT_TYPE","4","sourcecred","github","COMMIT","MDY6Q29tbWl0MjcxODg3MzcwOjVkNzVhZjYzZjk3YTk2MjQwOTVhMmE1MDhkMTUyZDNiZDlmMjk0ODc="],"dstIndex":26,"srcIndex":107,"timestampMs":1593614308000},{"address":["sourcecred","github","CORRESPONDS_TO_COMMIT_TYPE","4","sourcecred","github","COMMIT","MDY6Q29tbWl0MjcxODg3MzcwOjY0MzU2NzQyZWRkZTk2ZWJhOGY0Y2I2YTY0YzY5NDZiYTM2YjY3MTA="],"dstIndex":29,"srcIndex":108,"timestampMs":1597675149000},{"address":["sourcecred","github","CORRESPONDS_TO_COMMIT_TYPE","4","sourcecred","github","COMMIT","MDY6Q29tbWl0MjcxODg3MzcwOjY0NTJiMWM5Y2QxMzJmZTViNjBjNWJkOWE2ZDhmZTgxYmYwNzU4MDg="],"dstIndex":30,"srcIndex":109,"timestampMs":1598845968000},{"address":["sourcecred","github","CORRESPONDS_TO_COMMIT_TYPE","4","sourcecred","github","COMMIT","MDY6Q29tbWl0MjcxODg3MzcwOjY1OGYyYjE0ZGEyNGFhMmJmYTkwM2UxMGQ4Y2UyYzhkZWU1ZjE4MmI="],"dstIndex":31,"srcIndex":110,"timestampMs":1598841804000},{"address":["sourcecred","github","CORRESPONDS_TO_COMMIT_TYPE","4","sourcecred","github","COMMIT","MDY6Q29tbWl0MjcxODg3MzcwOjYxMDg1Y2I2NTA4Zjc4NjU2NjJmM2FjYzM4MGU5ZDhkNGY5ZWE3ZGY="],"dstIndex":27,"srcIndex":111,"timestampMs":1592504883000},{"address":["sourcecred","github","CORRESPONDS_TO_COMMIT_TYPE","4","sourcecred","github","COMMIT","MDY6Q29tbWl0MjcxODg3MzcwOjYxNjI0OTk3ZWY4ZDEwMGJhYjU4Y2JjMmRmMGUxYmJhYTVhNzhhMDI="],"dstIndex":28,"srcIndex":112,"timestampMs":1594225660000},{"address":["sourcecred","github","CORRESPONDS_TO_COMMIT_TYPE","4","sourcecred","github","COMMIT","MDY6Q29tbWl0MjcxODg3MzcwOjZjMmIwNzNjMjIzMjdmZmRmMWY1ZjU2YTk4YWY3M2FlNDZmNzFkNDM="],"dstIndex":32,"srcIndex":113,"timestampMs":1595387965000},{"address":["sourcecred","github","CORRESPONDS_TO_COMMIT_TYPE","4","sourcecred","github","COMMIT","MDY6Q29tbWl0MjcxODg3MzcwOjZkNGUzMDI1MzM1MjA2NjM5MjE4OWQzMDZhNmJlMDhhY2NhZmY3NDE="],"dstIndex":33,"srcIndex":114,"timestampMs":1598845983000},{"address":["sourcecred","github","CORRESPONDS_TO_COMMIT_TYPE","4","sourcecred","github","COMMIT","MDY6Q29tbWl0MjcxODg3MzcwOjZmY2NkMjYzYjhjMzU5YWI2NGYzNDNjYTI2YTYwNWJlNDRjOTBjM2E="],"dstIndex":34,"srcIndex":115,"timestampMs":1598463969000},{"address":["sourcecred","github","CORRESPONDS_TO_COMMIT_TYPE","4","sourcecred","github","COMMIT","MDY6Q29tbWl0MjcxODg3MzcwOjc1OTliOWVkZWVkZjg2OTdhYmIwOGNiMWM0YzdhNGVkZmQ1YTE5NGU="],"dstIndex":37,"srcIndex":116,"timestampMs":1598844760000},{"address":["sourcecred","github","CORRESPONDS_TO_COMMIT_TYPE","4","sourcecred","github","COMMIT","MDY6Q29tbWl0MjcxODg3MzcwOjc4Njg5ZDRjNzg3NTg0NDE0ZGE3NjFjNjM2YWU4NzU5NDAwMDE3Nzc="],"dstIndex":38,"srcIndex":117,"timestampMs":1596846528000},{"address":["sourcecred","github","CORRESPONDS_TO_COMMIT_TYPE","4","sourcecred","github","COMMIT","MDY6Q29tbWl0MjcxODg3MzcwOjc4YWU2NjFjMWZmNDJhZTlkYTA2ZThkNWNiMTBjZmYzOGQ3YjM2MGM="],"dstIndex":39,"srcIndex":118,"timestampMs":1598841044000},{"address":["sourcecred","github","CORRESPONDS_TO_COMMIT_TYPE","4","sourcecred","github","COMMIT","MDY6Q29tbWl0MjcxODg3MzcwOjcwNzI5ZTM2ODcxMDM4YTJlMzIwZTViYWMwMjg3YzNjNzRkMzE4ODc="],"dstIndex":35,"srcIndex":119,"timestampMs":1595463272000},{"address":["sourcecred","github","CORRESPONDS_TO_COMMIT_TYPE","4","sourcecred","github","COMMIT","MDY6Q29tbWl0MjcxODg3MzcwOjczYjcwZWJiYTZmODIyMTg2ODI5OTgzMjI3MDE0OWIyNzg5NGQ4ODI="],"dstIndex":36,"srcIndex":120,"timestampMs":1593518225000},{"address":["sourcecred","github","CORRESPONDS_TO_COMMIT_TYPE","4","sourcecred","github","COMMIT","MDY6Q29tbWl0MjcxODg3MzcwOjdiY2Y5ZTYyNTY4MDA2YjkxMzRmOTRjYmI2YWJhYWVkNzJlODI1ZWQ="],"dstIndex":40,"srcIndex":121,"timestampMs":1598841539000},{"address":["sourcecred","github","CORRESPONDS_TO_COMMIT_TYPE","4","sourcecred","github","COMMIT","MDY6Q29tbWl0MjcxODg3MzcwOjgxODA2OGE5NmM1MGFmNWM0YTc3NTk0ZjAwYzAxYmI0MTYwMGUzYTg="],"dstIndex":41,"srcIndex":122,"timestampMs":1595463249000},{"address":["sourcecred","github","CORRESPONDS_TO_COMMIT_TYPE","4","sourcecred","github","COMMIT","MDY6Q29tbWl0MjcxODg3MzcwOjgzMDczMTZkYmRhOWE0YTI3NmFiOGJjZDM0NzZhZDk3NjJkNTBiMDc="],"dstIndex":42,"srcIndex":123,"timestampMs":1593433916000},{"address":["sourcecred","github","CORRESPONDS_TO_COMMIT_TYPE","4","sourcecred","github","COMMIT","MDY6Q29tbWl0MjcxODg3MzcwOjhiY2MwMTZkMjgwNWY0OTBkMjZmMDJjMzZkMzVmNmZiNmYzNzcxMDE="],"dstIndex":43,"srcIndex":124,"timestampMs":1594232071000},{"address":["sourcecred","github","CORRESPONDS_TO_COMMIT_TYPE","4","sourcecred","github","COMMIT","MDY6Q29tbWl0MjcxODg3MzcwOjhjOWIyNWRhMWFiNmY4Yzg4Y2NjOGEzYzcxYWZlZWIwZjhjYzVlYmQ="],"dstIndex":44,"srcIndex":125,"timestampMs":1592439836000},{"address":["sourcecred","github","CORRESPONDS_TO_COMMIT_TYPE","4","sourcecred","github","COMMIT","MDY6Q29tbWl0MjcxODg3MzcwOjhkMzk2YzkzYWQ0OTgwNjM5NzkxYTk3NWJlMDBjMTdlYjJiYTY4NDU="],"dstIndex":45,"srcIndex":126,"timestampMs":1598844612000},{"address":["sourcecred","github","CORRESPONDS_TO_COMMIT_TYPE","4","sourcecred","github","COMMIT","MDY6Q29tbWl0MjcxODg3MzcwOjhlODMzNWU0MDU1NjViY2VjOWI0NDhlZmNmMjEzOTcyOTczYTZmMmM="],"dstIndex":46,"srcIndex":127,"timestampMs":1598835204000},{"address":["sourcecred","github","CORRESPONDS_TO_COMMIT_TYPE","4","sourcecred","github","COMMIT","MDY6Q29tbWl0MjcxODg3MzcwOjkwMzIyMDY5Mjk4ZWNkZDE2ZGFjY2MxZTFiNWQyYjY1ODRjODViZjU="],"dstIndex":47,"srcIndex":128,"timestampMs":1593518052000},{"address":["sourcecred","github","CORRESPONDS_TO_COMMIT_TYPE","4","sourcecred","github","COMMIT","MDY6Q29tbWl0MjcxODg3MzcwOjkxYWRlZTliMDk4YTg2N2MxYjY3OWJiM2UxYmFhMDkxNjg5ZjA3YWE="],"dstIndex":48,"srcIndex":129,"timestampMs":1593517954000},{"address":["sourcecred","github","CORRESPONDS_TO_COMMIT_TYPE","4","sourcecred","github","COMMIT","MDY6Q29tbWl0MjcxODg3MzcwOjljYzI2MGNlZjg3NTY1ODY1MTMyOWVjMTcxMGZjMDY5N2ZmMzI2ZDk="],"dstIndex":49,"srcIndex":130,"timestampMs":1594225941000},{"address":["sourcecred","github","CORRESPONDS_TO_COMMIT_TYPE","4","sourcecred","github","COMMIT","MDY6Q29tbWl0MjcxODg3MzcwOmE3OTZmNzExMDI2YTc1YzNhMzM3YWU4Njk2ZmUzZWU2MWNlNDdlMzg="],"dstIndex":50,"srcIndex":131,"timestampMs":1598845380000},{"address":["sourcecred","github","CORRESPONDS_TO_COMMIT_TYPE","4","sourcecred","github","COMMIT","MDY6Q29tbWl0MjcxODg3MzcwOmFmMTdmNTdjMTMwODkzZDBkMzhhN2NmZmNlZTAxMjEzMjIwYmFiYmI="],"dstIndex":51,"srcIndex":132,"timestampMs":1595463066000},{"address":["sourcecred","github","CORRESPONDS_TO_COMMIT_TYPE","4","sourcecred","github","COMMIT","MDY6Q29tbWl0MjcxODg3MzcwOmI0OWE3MThkMmVmNzA3ODdkZDU1YjM4ZWUxZTE3MWNmZjk0OTkxZDY="],"dstIndex":54,"srcIndex":133,"timestampMs":1598480182000},{"address":["sourcecred","github","CORRESPONDS_TO_COMMIT_TYPE","4","sourcecred","github","COMMIT","MDY6Q29tbWl0MjcxODg3MzcwOmI1MWZhZGQ5MjFiODcyNGE0OTBjOWQ1N2FmMjQ1ZTRlYzUwOTdjMzc="],"dstIndex":55,"srcIndex":134,"timestampMs":1592504952000},{"address":["sourcecred","github","CORRESPONDS_TO_COMMIT_TYPE","4","sourcecred","github","COMMIT","MDY6Q29tbWl0MjcxODg3MzcwOmI2YTJlNjY5ZWEyNWIzOTMwMTAxNmE2N2UzNmZhYzU4MDFlODgyM2I="],"dstIndex":56,"srcIndex":135,"timestampMs":1598842292000},{"address":["sourcecred","github","CORRESPONDS_TO_COMMIT_TYPE","4","sourcecred","github","COMMIT","MDY6Q29tbWl0MjcxODg3MzcwOmIyM2ZkMTE5MTBkMjg4YjYxNTM5NjVjYjQ1NzYzNTFjODgwNjI1ZjQ="],"dstIndex":52,"srcIndex":136,"timestampMs":1598896748000},{"address":["sourcecred","github","CORRESPONDS_TO_COMMIT_TYPE","4","sourcecred","github","COMMIT","MDY6Q29tbWl0MjcxODg3MzcwOmIzMmRhNDg2ZjdmMGEwZmM1OWM2ODk2MjQ4ODA0NGIwZmFhNmZiNDA="],"dstIndex":53,"srcIndex":137,"timestampMs":1592440477000},{"address":["sourcecred","github","CORRESPONDS_TO_COMMIT_TYPE","4","sourcecred","github","COMMIT","MDY6Q29tbWl0MjcxODg3MzcwOmJhYWQ2NWVhMDZhNjA1MWFiMDkwM2NmNzcxMzIzNTFhMWNhN2YwOTM="],"dstIndex":57,"srcIndex":138,"timestampMs":1595303914000},{"address":["sourcecred","github","CORRESPONDS_TO_COMMIT_TYPE","4","sourcecred","github","COMMIT","MDY6Q29tbWl0MjcxODg3MzcwOmM2YmU2OTBmYmVmYzg5MjU0ODdhZjUxNDYzZDZkODhhOTBhNDAxZTY="],"dstIndex":58,"srcIndex":139,"timestampMs":1592838315000},{"address":["sourcecred","github","CORRESPONDS_TO_COMMIT_TYPE","4","sourcecred","github","COMMIT","MDY6Q29tbWl0MjcxODg3MzcwOmNiNjZiNDU4NTU3ZDhhNGI2ZGRiYjIzOTE1NGU2OTMxYTEwNWU4M2E="],"dstIndex":59,"srcIndex":140,"timestampMs":1598836339000},{"address":["sourcecred","github","CORRESPONDS_TO_COMMIT_TYPE","4","sourcecred","github","COMMIT","MDY6Q29tbWl0MjcxODg3MzcwOmQ1MWUyZjcyMTkzY2QzOTlhYzI4ZTJkMmI5Mzg5NGI2ZDc4NmY3OTM="],"dstIndex":61,"srcIndex":141,"timestampMs":1599616092000},{"address":["sourcecred","github","CORRESPONDS_TO_COMMIT_TYPE","4","sourcecred","github","COMMIT","MDY6Q29tbWl0MjcxODg3MzcwOmQ2ZmI2YzE4NDg4ZTA2YzI1NTk4MDhjZGM3OTQ0YTBkOTMwMWNmMzk="],"dstIndex":62,"srcIndex":142,"timestampMs":1595519490000},{"address":["sourcecred","github","CORRESPONDS_TO_COMMIT_TYPE","4","sourcecred","github","COMMIT","MDY6Q29tbWl0MjcxODg3MzcwOmQ4NTZlN2YzYzZmYzBlOWJkZDk1MjRhYzI5Y2M3ZWE3MGY5Nzc5YWQ="],"dstIndex":63,"srcIndex":143,"timestampMs":1598840438000},{"address":["sourcecred","github","CORRESPONDS_TO_COMMIT_TYPE","4","sourcecred","github","COMMIT","MDY6Q29tbWl0MjcxODg3MzcwOmQyNWVkMjQ0NWNkM2VmYjAwMGNiYjIyYTRhZjliMGY0NWIyY2E0OTI="],"dstIndex":60,"srcIndex":144,"timestampMs":1593468514000},{"address":["sourcecred","github","CORRESPONDS_TO_COMMIT_TYPE","4","sourcecred","github","COMMIT","MDY6Q29tbWl0MjcxODg3MzcwOmRmZDZlMDM4OTBiNDdkYWYyZThiMWVkNDUwMzY3MjM0OWIwMDk1NTU="],"dstIndex":64,"srcIndex":145,"timestampMs":1593432420000},{"address":["sourcecred","github","CORRESPONDS_TO_COMMIT_TYPE","4","sourcecred","github","COMMIT","MDY6Q29tbWl0MjcxODg3MzcwOmU4NTk4YTBkYWY1MzFmZWY3ODhkNTQ5MWUxOTI4MTEzNGJjYTIxYzA="],"dstIndex":68,"srcIndex":146,"timestampMs":1598836209000},{"address":["sourcecred","github","CORRESPONDS_TO_COMMIT_TYPE","4","sourcecred","github","COMMIT","MDY6Q29tbWl0MjcxODg3MzcwOmUyMWRmOTY5M2UxYjQyYjc5ZDExYjNjNGUwZGJjMjVkNzNhMTY4NDQ="],"dstIndex":65,"srcIndex":147,"timestampMs":1598836293000},{"address":["sourcecred","github","CORRESPONDS_TO_COMMIT_TYPE","4","sourcecred","github","COMMIT","MDY6Q29tbWl0MjcxODg3MzcwOmUyYzk3NjgwZGE2NmI0YTU5OTZkNTI2MTExMjNjYjdmNjk1MDMyM2I="],"dstIndex":66,"srcIndex":148,"timestampMs":1598835325000},{"address":["sourcecred","github","CORRESPONDS_TO_COMMIT_TYPE","4","sourcecred","github","COMMIT","MDY6Q29tbWl0MjcxODg3MzcwOmUzZDhjM2U1OTEzMGE0MjliZTA1MDVlY2U2YWExYmJlOTk4NDc4MjU="],"dstIndex":67,"srcIndex":149,"timestampMs":1593010586000},{"address":["sourcecred","github","CORRESPONDS_TO_COMMIT_TYPE","4","sourcecred","github","COMMIT","MDY6Q29tbWl0MjcxODg3MzcwOmVhOGVjOGYxNDJmOTNjNjgxZDMxNzhkYzgyZjVjMzBkOGI3Mzg2OTI="],"dstIndex":69,"srcIndex":150,"timestampMs":1598841799000},{"address":["sourcecred","github","CORRESPONDS_TO_COMMIT_TYPE","4","sourcecred","github","COMMIT","MDY6Q29tbWl0MjcxODg3MzcwOmVhYWZlNDNkODgwODJhMTNhYWM4NzYyMWQ2YzViNjIwOTk4NDEzMDQ="],"dstIndex":70,"srcIndex":151,"timestampMs":1597694366000},{"address":["sourcecred","github","CORRESPONDS_TO_COMMIT_TYPE","4","sourcecred","github","COMMIT","MDY6Q29tbWl0MjcxODg3MzcwOmVjZjczMWQyYjU0NzlhN2NiODJlZGVkMzhlZmNjYWM0ZDA4NTBiNTE="],"dstIndex":71,"srcIndex":152,"timestampMs":1599615947000},{"address":["sourcecred","github","CORRESPONDS_TO_COMMIT_TYPE","4","sourcecred","github","COMMIT","MDY6Q29tbWl0MjcxODg3MzcwOmVkM2Q4NGRhZmQ3ZTkzNDEwY2E4YjI0OGQxN2FhMzRhMTkwOTdjMDA="],"dstIndex":72,"srcIndex":153,"timestampMs":1598840697000},{"address":["sourcecred","github","CORRESPONDS_TO_COMMIT_TYPE","4","sourcecred","github","COMMIT","MDY6Q29tbWl0MjcxODg3MzcwOmY0Mjk5MjBhZDc4Y2Q3Mjk4NWFiZmVmZjkxYzBkMjFjY2RmYjQ4MTY="],"dstIndex":73,"srcIndex":154,"timestampMs":1598836079000},{"address":["sourcecred","github","CORRESPONDS_TO_COMMIT_TYPE","4","sourcecred","github","COMMIT","MDY6Q29tbWl0MjcxODg3MzcwOmZmN2ZiYTEwNDJiNDQ2ZWM0MzY5OGUwNDM4OWVkYjk4YmJkN2E2M2I="],"dstIndex":75,"srcIndex":155,"timestampMs":1598841108000},{"address":["sourcecred","github","CORRESPONDS_TO_COMMIT_TYPE","4","sourcecred","github","COMMIT","MDY6Q29tbWl0MjcxODg3MzcwOmZmNGIzZjFmMmEwYmI3N2ZjMjYyZWJjYWZiMWI2N2I4OGVjYjM5ODg="],"dstIndex":74,"srcIndex":156,"timestampMs":1593613895000},{"address":["sourcecred","github","HAS_PARENT","6","sourcecred","github","PULL","SecretFoundation","SecretWiki","1"],"dstIndex":164,"srcIndex":157,"timestampMs":1595303916000},{"address":["sourcecred","github","HAS_PARENT","6","sourcecred","github","PULL","SecretFoundation","SecretWiki","2"],"dstIndex":164,"srcIndex":158,"timestampMs":1595463452000},{"address":["sourcecred","github","HAS_PARENT","6","sourcecred","github","PULL","SecretFoundation","SecretWiki","3"],"dstIndex":164,"srcIndex":159,"timestampMs":1596340266000},{"address":["sourcecred","github","HAS_PARENT","6","sourcecred","github","PULL","SecretFoundation","SecretWiki","4"],"dstIndex":164,"srcIndex":160,"timestampMs":1596846530000},{"address":["sourcecred","github","HAS_PARENT","6","sourcecred","github","PULL","SecretFoundation","SecretWiki","5"],"dstIndex":164,"srcIndex":161,"timestampMs":1598840801000},{"address":["sourcecred","github","HAS_PARENT","6","sourcecred","github","PULL","SecretFoundation","SecretWiki","6"],"dstIndex":164,"srcIndex":162,"timestampMs":1599013086000},{"address":["sourcecred","github","HAS_PARENT","6","sourcecred","github","PULL","SecretFoundation","SecretWiki","7"],"dstIndex":164,"srcIndex":163,"timestampMs":1599616004000},{"address":["sourcecred","github","HAS_PARENT","8","sourcecred","github","COMMENT","PULL","SecretFoundation","SecretWiki","5","683518918"],"dstIndex":161,"srcIndex":76,"timestampMs":1598841205000},{"address":["sourcecred","github","HAS_PARENT","8","sourcecred","github","COMMENT","PULL","SecretFoundation","SecretWiki","5","683523498"],"dstIndex":161,"srcIndex":77,"timestampMs":1598842521000},{"address":["sourcecred","github","HAS_PARENT","8","sourcecred","github","COMMENT","PULL","SecretFoundation","SecretWiki","6","685292773"],"dstIndex":162,"srcIndex":78,"timestampMs":1599022000000},{"address":["sourcecred","github","HAS_PARENT","8","sourcecred","github","COMMENT","PULL","SecretFoundation","SecretWiki","6","689233361"],"dstIndex":162,"srcIndex":79,"timestampMs":1599613142000},{"address":["sourcecred","github","HAS_PARENT","8","sourcecred","github","COMMENT","PULL","SecretFoundation","SecretWiki","6","691184387"],"dstIndex":162,"srcIndex":80,"timestampMs":1599840575000},{"address":["sourcecred","github","MERGED_AS","6","sourcecred","github","PULL","SecretFoundation","SecretWiki","1"],"dstIndex":82,"srcIndex":157,"timestampMs":1595519141000},{"address":["sourcecred","github","MERGED_AS","6","sourcecred","github","PULL","SecretFoundation","SecretWiki","2"],"dstIndex":142,"srcIndex":158,"timestampMs":1595519490000},{"address":["sourcecred","github","MERGED_AS","6","sourcecred","github","PULL","SecretFoundation","SecretWiki","3"],"dstIndex":109,"srcIndex":159,"timestampMs":1598845968000},{"address":["sourcecred","github","MERGED_AS","6","sourcecred","github","PULL","SecretFoundation","SecretWiki","4"],"dstIndex":114,"srcIndex":160,"timestampMs":1598845983000},{"address":["sourcecred","github","MERGED_AS","6","sourcecred","github","PULL","SecretFoundation","SecretWiki","5"],"dstIndex":126,"srcIndex":161,"timestampMs":1598844612000},{"address":["sourcecred","github","MERGED_AS","6","sourcecred","github","PULL","SecretFoundation","SecretWiki","7"],"dstIndex":141,"srcIndex":163,"timestampMs":1599616092000},{"address":["sourcecred","github","REACTS","THUMBS_UP","5","sourcecred","github","USERLIKE","USER","jlwaugh","8","sourcecred","github","COMMENT","PULL","SecretFoundation","SecretWiki","6","689233361"],"dstIndex":79,"srcIndex":166,"timestampMs":1599614165000},{"address":["sourcecred","github","REACTS","THUMBS_UP","5","sourcecred","github","USERLIKE","USER","mohammedpatla","8","sourcecred","github","COMMENT","PULL","SecretFoundation","SecretWiki","5","683518918"],"dstIndex":76,"srcIndex":168,"timestampMs":1598841347000},{"address":["sourcecred","github","REACTS","THUMBS_UP","5","sourcecred","github","USERLIKE","USER","moonstash","8","sourcecred","github","COMMENT","PULL","SecretFoundation","SecretWiki","6","689233361"],"dstIndex":79,"srcIndex":169,"timestampMs":1599615348000},{"address":["sourcecred","github","REFERENCES","4","sourcecred","github","COMMIT","MDY6Q29tbWl0MjcxODg3MzcwOjA3YmM4MDBiMTU5MzkzNWQ1NzYyZGQ1ZDQ4OWIyYzMwY2Q2NTAyM2U=","6","sourcecred","github","PULL","SecretFoundation","SecretWiki","1"],"dstIndex":157,"srcIndex":82,"timestampMs":1595519141000},{"address":["sourcecred","github","REFERENCES","4","sourcecred","github","COMMIT","MDY6Q29tbWl0MjcxODg3MzcwOjAxMGQ0ZWJhODk1ODk5ZDMwMjM3MjYwZmE4YmNkNjQ3NWYyYjg5OGQ=","6","sourcecred","github","PULL","SecretFoundation","SecretWiki","3"],"dstIndex":159,"srcIndex":84,"timestampMs":1598840215000},{"address":["sourcecred","github","REFERENCES","4","sourcecred","github","COMMIT","MDY6Q29tbWl0MjcxODg3MzcwOjIyMjY5ODcxMDRiM2JmM2IwOTBhMWU1NDM2YjAwMDc0ZGVlOWQ2MGM=","6","sourcecred","github","PULL","SecretFoundation","SecretWiki","5"],"dstIndex":161,"srcIndex":92,"timestampMs":1598842388000},{"address":["sourcecred","github","REFERENCES","4","sourcecred","github","COMMIT","MDY6Q29tbWl0MjcxODg3MzcwOjY0NTJiMWM5Y2QxMzJmZTViNjBjNWJkOWE2ZDhmZTgxYmYwNzU4MDg=","6","sourcecred","github","PULL","SecretFoundation","SecretWiki","3"],"dstIndex":159,"srcIndex":109,"timestampMs":1598845968000},{"address":["sourcecred","github","REFERENCES","4","sourcecred","github","COMMIT","MDY6Q29tbWl0MjcxODg3MzcwOjZkNGUzMDI1MzM1MjA2NjM5MjE4OWQzMDZhNmJlMDhhY2NhZmY3NDE=","6","sourcecred","github","PULL","SecretFoundation","SecretWiki","4"],"dstIndex":160,"srcIndex":114,"timestampMs":1598845983000},{"address":["sourcecred","github","REFERENCES","4","sourcecred","github","COMMIT","MDY6Q29tbWl0MjcxODg3MzcwOjcwNzI5ZTM2ODcxMDM4YTJlMzIwZTViYWMwMjg3YzNjNzRkMzE4ODc=","6","sourcecred","github","PULL","SecretFoundation","SecretWiki","2"],"dstIndex":158,"srcIndex":119,"timestampMs":1595463272000},{"address":["sourcecred","github","REFERENCES","4","sourcecred","github","COMMIT","MDY6Q29tbWl0MjcxODg3MzcwOjhkMzk2YzkzYWQ0OTgwNjM5NzkxYTk3NWJlMDBjMTdlYjJiYTY4NDU=","6","sourcecred","github","PULL","SecretFoundation","SecretWiki","5"],"dstIndex":161,"srcIndex":126,"timestampMs":1598844612000},{"address":["sourcecred","github","REFERENCES","4","sourcecred","github","COMMIT","MDY6Q29tbWl0MjcxODg3MzcwOmFmMTdmNTdjMTMwODkzZDBkMzhhN2NmZmNlZTAxMjEzMjIwYmFiYmI=","6","sourcecred","github","PULL","SecretFoundation","SecretWiki","1"],"dstIndex":157,"srcIndex":132,"timestampMs":1595463066000},{"address":["sourcecred","github","REFERENCES","4","sourcecred","github","COMMIT","MDY6Q29tbWl0MjcxODg3MzcwOmQ1MWUyZjcyMTkzY2QzOTlhYzI4ZTJkMmI5Mzg5NGI2ZDc4NmY3OTM=","6","sourcecred","github","PULL","SecretFoundation","SecretWiki","7"],"dstIndex":163,"srcIndex":141,"timestampMs":1599616092000},{"address":["sourcecred","github","REFERENCES","4","sourcecred","github","COMMIT","MDY6Q29tbWl0MjcxODg3MzcwOmQ2ZmI2YzE4NDg4ZTA2YzI1NTk4MDhjZGM3OTQ0YTBkOTMwMWNmMzk=","6","sourcecred","github","PULL","SecretFoundation","SecretWiki","2"],"dstIndex":158,"srcIndex":142,"timestampMs":1595519490000},{"address":["sourcecred","github","REFERENCES","4","sourcecred","github","COMMIT","MDY6Q29tbWl0MjcxODg3MzcwOmQ4NTZlN2YzYzZmYzBlOWJkZDk1MjRhYzI5Y2M3ZWE3MGY5Nzc5YWQ=","6","sourcecred","github","PULL","SecretFoundation","SecretWiki","4"],"dstIndex":160,"srcIndex":143,"timestampMs":1598840438000},{"address":["sourcecred","github","REFERENCES","6","sourcecred","github","PULL","SecretFoundation","SecretWiki","5","5","sourcecred","github","USERLIKE","USER","jlwaugh"],"dstIndex":166,"srcIndex":161,"timestampMs":1598840801000},{"address":["sourcecred","github","REFERENCES","8","sourcecred","github","COMMENT","PULL","SecretFoundation","SecretWiki","5","683523498","5","sourcecred","github","USERLIKE","USER","moonstash"],"dstIndex":169,"srcIndex":77,"timestampMs":1598842521000}],"nodes":[{"description":"[comment](https://github.com/SecretFoundation/SecretWiki/pull/5#issuecomment-683518918) on [#5](https://github.com/SecretFoundation/SecretWiki/pull/5): Added link to the Working Document for SGX support","index":76,"timestampMs":1598841205000},{"description":"[comment](https://github.com/SecretFoundation/SecretWiki/pull/5#issuecomment-683523498) on [#5](https://github.com/SecretFoundation/SecretWiki/pull/5): Added link to the Working Document for SGX support","index":77,"timestampMs":1598842521000},{"description":"[comment](https://github.com/SecretFoundation/SecretWiki/pull/6#issuecomment-685292773) on [#6](https://github.com/SecretFoundation/SecretWiki/pull/6): The dusky","index":78,"timestampMs":1599022000000},{"description":"[comment](https://github.com/SecretFoundation/SecretWiki/pull/6#issuecomment-689233361) on [#6](https://github.com/SecretFoundation/SecretWiki/pull/6): The dusky","index":79,"timestampMs":1599613142000},{"description":"[comment](https://github.com/SecretFoundation/SecretWiki/pull/6#issuecomment-691184387) on [#6](https://github.com/SecretFoundation/SecretWiki/pull/6): The dusky","index":80,"timestampMs":1599840575000},{"description":"[04ee7fd](https://github.com/SecretFoundation/SecretWiki/commit/04ee7fd4259e25e80646c40773bed2fe55ac1316): Update sgx.md","index":81,"timestampMs":1598842730000},{"description":"[07bc800](https://github.com/SecretFoundation/SecretWiki/commit/07bc800b1593935d5762dd5d489b2c30cd65023e): Merge pull request #1 from SecretFoundation/dependabot/npm_and_yarn/lodash-4.17.19","index":82,"timestampMs":1595519141000},{"description":"[09b8b5d](https://github.com/SecretFoundation/SecretWiki/commit/09b8b5d757916d4fb73d2da9c7cb4e019258056d): updating network info","index":83,"timestampMs":1598358973000},{"description":"[010d4eb](https://github.com/SecretFoundation/SecretWiki/commit/010d4eba895899d30237260fa8bcd6475f2b898d): Merge pull request #3 from SecretFoundation/master","index":84,"timestampMs":1598840215000},{"description":"[0e96bbf](https://github.com/SecretFoundation/SecretWiki/commit/0e96bbf496973694a71849f16e6629ec799073fe): Update broken links, and added a project","index":85,"timestampMs":1598841523000},{"description":"[14abd3c](https://github.com/SecretFoundation/SecretWiki/commit/14abd3cba611749f7caf4ce18e43f22d6bb43a85): Update index.md","index":86,"timestampMs":1592498548000},{"description":"[1770c2b](https://github.com/SecretFoundation/SecretWiki/commit/1770c2b8324ce83a3771c4644ee21c17f53cdab1): updating foundation","index":87,"timestampMs":1593433030000},{"description":"[1e9b855](https://github.com/SecretFoundation/SecretWiki/commit/1e9b855b2b5413e89aafb02a7c5d87dd7a912d62): updating index page","index":88,"timestampMs":1593010444000},{"description":"[1fd8dcb](https://github.com/SecretFoundation/SecretWiki/commit/1fd8dcb165322e5816e2e5cc5baca41a1c797f25): remove deploy.sh","index":89,"timestampMs":1592440618000},{"description":"[2494bb4](https://github.com/SecretFoundation/SecretWiki/commit/2494bb4f2f2398cbfba70ded6fcf71eac036c714): Update sgx.md","index":90,"timestampMs":1598844118000},{"description":"[26bb2bc](https://github.com/SecretFoundation/SecretWiki/commit/26bb2bca2de1a739fcbb39a9339066cbe2084fcf): Changed Nav Bar & Intoruduction, Added Projects","index":91,"timestampMs":1594950359000},{"description":"[2226987](https://github.com/SecretFoundation/SecretWiki/commit/2226987104b3bf3b090a1e5436b00074dee9d60c): Merge pull request #5 from SecretFoundation/master","index":92,"timestampMs":1598842388000},{"description":"[35360b6](https://github.com/SecretFoundation/SecretWiki/commit/35360b654a1b81fdfd45245a74c923c81b4696c0): Updated sgx.md","index":93,"timestampMs":1598962848000},{"description":"[3810ef1](https://github.com/SecretFoundation/SecretWiki/commit/3810ef1cf34a101e170328b09d4599ef0b21d06c): Bump elliptic from 6.5.2 to 6.5.3","index":94,"timestampMs":1596340264000},{"description":"[315f57e](https://github.com/SecretFoundation/SecretWiki/commit/315f57ef13b358fca24bbfaebe50ff825c9f09ce): Update sgx.md","index":95,"timestampMs":1598904675000},{"description":"[31ea5a1](https://github.com/SecretFoundation/SecretWiki/commit/31ea5a10dd2cc0731d3a64e75547dfb036bb1d79): updating FAQ","index":96,"timestampMs":1598293405000},{"description":"[33aa8c9](https://github.com/SecretFoundation/SecretWiki/commit/33aa8c92cfdbc80a756ac9d371ce7cc1785bc224): updating FAQ","index":97,"timestampMs":1595697005000},{"description":"[3f61905](https://github.com/SecretFoundation/SecretWiki/commit/3f61905b71145f54a8a2629304e6a415816a62b1): Updated Structure For Wiki","index":98,"timestampMs":1595462947000},{"description":"[49990fe](https://github.com/SecretFoundation/SecretWiki/commit/49990fea127701776947930a7534b3adae0fc8e6): Update README.md","index":99,"timestampMs":1598536432000},{"description":"[41d0fe7](https://github.com/SecretFoundation/SecretWiki/commit/41d0fe73606db574a5ff4046906881f20f9c2297): Update sgx.md","index":100,"timestampMs":1598963064000},{"description":"[4234584](https://github.com/SecretFoundation/SecretWiki/commit/4234584956e1e4552b36fed7e7355a43c03bdfae): Update README.md","index":101,"timestampMs":1598482674000},{"description":"[4cfdd04](https://github.com/SecretFoundation/SecretWiki/commit/4cfdd04dcae7b1a4e0056aba0debaed808600ab8): formatting fix","index":102,"timestampMs":1598293530000},{"description":"[5536a46](https://github.com/SecretFoundation/SecretWiki/commit/5536a46da6a8e68aeefe092492e62ce5765e4289): updates","index":103,"timestampMs":1595944822000},{"description":"[506d211](https://github.com/SecretFoundation/SecretWiki/commit/506d211e7ab9e784e8523e8910754672b800eeb8): Update README.md","index":104,"timestampMs":1594226903000},{"description":"[515302f](https://github.com/SecretFoundation/SecretWiki/commit/515302fe4bfc3744114bcbbb3ec03f344d243455): Update config.js","index":105,"timestampMs":1598844890000},{"description":"[5d371e5](https://github.com/SecretFoundation/SecretWiki/commit/5d371e5b5a749d0fbd8e7948fbef392a2e7ad3d0): small FAQ edits","index":106,"timestampMs":1593518164000},{"description":"[5d75af6](https://github.com/SecretFoundation/SecretWiki/commit/5d75af63f97a9624095a2a508d152d3bd9f29487): brevity","index":107,"timestampMs":1593614308000},{"description":"[6435674](https://github.com/SecretFoundation/SecretWiki/commit/64356742edde96eba8f4cb6a64c6946ba36b6710): updating foundation page","index":108,"timestampMs":1597675149000},{"description":"[6452b1c](https://github.com/SecretFoundation/SecretWiki/commit/6452b1c9cd132fe5b60c5bd9a6d8fe81bf075808): Merge pull request #3 from SecretFoundation/dependabot/npm_and_yarn/elliptic-6.5.3","index":109,"timestampMs":1598845968000},{"description":"[658f2b1](https://github.com/SecretFoundation/SecretWiki/commit/658f2b14da24aa2bfa903e10d8ce2c8dee5f182b): Update sgx.md","index":110,"timestampMs":1598841804000},{"description":"[61085cb](https://github.com/SecretFoundation/SecretWiki/commit/61085cb6508f7865662f3acc380e9d8d4f9ea7df): buttons","index":111,"timestampMs":1592504883000},{"description":"[6162499](https://github.com/SecretFoundation/SecretWiki/commit/61624997ef8d100bab58cbc2df0e1bbaa5a78a02): Update config.js","index":112,"timestampMs":1594225660000},{"description":"[6c2b073](https://github.com/SecretFoundation/SecretWiki/commit/6c2b073c22327ffdf1f5f56a98af73ae46f71d43): Create committees.md","index":113,"timestampMs":1595387965000},{"description":"[6d4e302](https://github.com/SecretFoundation/SecretWiki/commit/6d4e30253352066392189d306a6be08accaff741): Merge pull request #4 from SecretFoundation/dependabot/npm_and_yarn/prismjs-1.21.0","index":114,"timestampMs":1598845983000},{"description":"[6fccd26](https://github.com/SecretFoundation/SecretWiki/commit/6fccd263b8c359ab64f343ca26a605be44c90c3a): fixing typo on dates","index":115,"timestampMs":1598463969000},{"description":"[7599b9e](https://github.com/SecretFoundation/SecretWiki/commit/7599b9edeedf8697abb08cb1c4c7a4edfd5a194e): Update sgx.md","index":116,"timestampMs":1598844760000},{"description":"[78689d4](https://github.com/SecretFoundation/SecretWiki/commit/78689d4c787584414da761c636ae875940001777): Bump prismjs from 1.20.0 to 1.21.0","index":117,"timestampMs":1596846528000},{"description":"[78ae661](https://github.com/SecretFoundation/SecretWiki/commit/78ae661c1ff42ae9da06e8d5cb10cff38d7b360c): Create validators.md","index":118,"timestampMs":1598841044000},{"description":"[70729e3](https://github.com/SecretFoundation/SecretWiki/commit/70729e36871038a2e320e5bac0287c3c74d31887): Merge pull request #2 from mohammedpatla/mohd_doc","index":119,"timestampMs":1595463272000},{"description":"[73b70eb](https://github.com/SecretFoundation/SecretWiki/commit/73b70ebba6f8221868299832270149b27894d882): making documentation links quotes","index":120,"timestampMs":1593518225000},{"description":"[7bcf9e6](https://github.com/SecretFoundation/SecretWiki/commit/7bcf9e62568006b9134f94cbb6abaaed72e825ed): Update sgx.md","index":121,"timestampMs":1598841539000},{"description":"[818068a](https://github.com/SecretFoundation/SecretWiki/commit/818068a96c50af5c4a77594f00c01bb41600e3a8): Merge branch 'master' into mohd_doc","index":122,"timestampMs":1595463249000},{"description":"[8307316](https://github.com/SecretFoundation/SecretWiki/commit/8307316dbda9a4a276ab8bcd3476ad9762d50b07): updating network info page","index":123,"timestampMs":1593433916000},{"description":"[8bcc016](https://github.com/SecretFoundation/SecretWiki/commit/8bcc016d2805f490d26f02c36d35f6fb6f377101): Update tutorials.md","index":124,"timestampMs":1594232071000},{"description":"[8c9b25d](https://github.com/SecretFoundation/SecretWiki/commit/8c9b25da1ab6f8c88ccc8a3c71afeeb0f8cc5ebd): deploy","index":125,"timestampMs":1592439836000},{"description":"[8d396c9](https://github.com/SecretFoundation/SecretWiki/commit/8d396c93ad4980639791a975be00c17eb2ba6845): Merge pull request #5 from mohammedpatla/mohd_doc","index":126,"timestampMs":1598844612000},{"description":"[8e8335e](https://github.com/SecretFoundation/SecretWiki/commit/8e8335e405565bcec9b448efcf213972973a6f2c): Update config.js","index":127,"timestampMs":1598835204000},{"description":"[9032206](https://github.com/SecretFoundation/SecretWiki/commit/90322069298ecdd16daccc1e1b5d2b6584c85bf5): small FAQ edits","index":128,"timestampMs":1593518052000},{"description":"[91adee9](https://github.com/SecretFoundation/SecretWiki/commit/91adee9b098a867c1b679bb3e1baa091689f07aa): updating and reordering FAQ","index":129,"timestampMs":1593517954000},{"description":"[9cc260c](https://github.com/SecretFoundation/SecretWiki/commit/9cc260cef875658651329ec1710fc0697ff326d9): Create tutorials.md","index":130,"timestampMs":1594225941000},{"description":"[a796f71](https://github.com/SecretFoundation/SecretWiki/commit/a796f711026a75c3a337ae8696fe3ee61ce47e38): Update sgx.md","index":131,"timestampMs":1598845380000},{"description":"[af17f57](https://github.com/SecretFoundation/SecretWiki/commit/af17f57c130893d0d38a7cffcee01213220babbb): Merge pull request #1 from SecretFoundation/master","index":132,"timestampMs":1595463066000},{"description":"[b49a718](https://github.com/SecretFoundation/SecretWiki/commit/b49a718d2ef70787dd55b38ee1e171cff94991d6): Update config.js","index":133,"timestampMs":1598480182000},{"description":"[b51fadd](https://github.com/SecretFoundation/SecretWiki/commit/b51fadd921b8724a490c9d57af245e4ec5097c37): fix","index":134,"timestampMs":1592504952000},{"description":"[b6a2e66](https://github.com/SecretFoundation/SecretWiki/commit/b6a2e669ea25b39301016a67e36fac5801e8823b): Merge SecretFoundation-master","index":135,"timestampMs":1598842292000},{"description":"[b23fd11](https://github.com/SecretFoundation/SecretWiki/commit/b23fd11910d288b6153965cb4576351c880625f4): update committees.md","index":136,"timestampMs":1598896748000},{"description":"[b32da48](https://github.com/SecretFoundation/SecretWiki/commit/b32da486f7f0a0fc59c68962488044b0faa6fb40): norm","index":137,"timestampMs":1592440477000},{"description":"[baad65e](https://github.com/SecretFoundation/SecretWiki/commit/baad65ea06a6051ab0903cf77132351a1ca7f093): Bump lodash from 4.17.15 to 4.17.19","index":138,"timestampMs":1595303914000},{"description":"[c6be690](https://github.com/SecretFoundation/SecretWiki/commit/c6be690fbefc8925487af51463d6d88a90a401e6): FAQ updates","index":139,"timestampMs":1592838315000},{"description":"[cb66b45](https://github.com/SecretFoundation/SecretWiki/commit/cb66b458557d8a4b6ddbb239154e6931a105e83a): Create sgx.md","index":140,"timestampMs":1598836339000},{"description":"[d51e2f7](https://github.com/SecretFoundation/SecretWiki/commit/d51e2f72193cd399ac28e2d2b93894b6d786f793): Merge pull request #7 from the-dusky/the_dusky_one_page","index":141,"timestampMs":1599616092000},{"description":"[d6fb6c1](https://github.com/SecretFoundation/SecretWiki/commit/d6fb6c18488e06c2559808cdc7944a0d9301cf39): Merge pull request #2 from mohammedpatla/mohd_doc","index":142,"timestampMs":1595519490000},{"description":"[d856e7f](https://github.com/SecretFoundation/SecretWiki/commit/d856e7f3c6fc0e9bdd9524ac29cc7ea70f9779ad): Merge pull request #4 from mohammedpatla/master","index":143,"timestampMs":1598840438000},{"description":"[d25ed24](https://github.com/SecretFoundation/SecretWiki/commit/d25ed2445cd3efb000cbb22a4af9b0f45b2ca492): updating FAQ","index":144,"timestampMs":1593468514000},{"description":"[dfd6e03](https://github.com/SecretFoundation/SecretWiki/commit/dfd6e03890b47daf2e8b1ed4503672349b009555): Updating the FAQ","index":145,"timestampMs":1593432420000},{"description":"[e8598a0](https://github.com/SecretFoundation/SecretWiki/commit/e8598a0daf531fef788d5491e19281134bca21c0): Update config.js","index":146,"timestampMs":1598836209000},{"description":"[e21df96](https://github.com/SecretFoundation/SecretWiki/commit/e21df9693e1b42b79d11b3c4e0dbc25d73a16844): Update config.js","index":147,"timestampMs":1598836293000},{"description":"[e2c9768](https://github.com/SecretFoundation/SecretWiki/commit/e2c97680da66b4a5996d52611123cb7f6950323b): Create Infrastructure Committee file","index":148,"timestampMs":1598835325000},{"description":"[e3d8c3e](https://github.com/SecretFoundation/SecretWiki/commit/e3d8c3e59130a429be0505ece6aa1bbe99847825): editing buttons","index":149,"timestampMs":1593010586000},{"description":"[ea8ec8f](https://github.com/SecretFoundation/SecretWiki/commit/ea8ec8f142f93c681d3178dc82f5c30d8b738692): Update Projects","index":150,"timestampMs":1598841799000},{"description":"[eaafe43](https://github.com/SecretFoundation/SecretWiki/commit/eaafe43d88082a13aac87621d6c5b62099841304): adding awareness committee","index":151,"timestampMs":1597694366000},{"description":"[ecf731d](https://github.com/SecretFoundation/SecretWiki/commit/ecf731d2b5479a7cb82eded38efccac4d0850b51): Psychz Updates to the SGX.md page","index":152,"timestampMs":1599615947000},{"description":"[ed3d84d](https://github.com/SecretFoundation/SecretWiki/commit/ed3d84dafd7e93410ca8b248d17aa34a19097c00): Added link to working document for sgx hardware","index":153,"timestampMs":1598840697000},{"description":"[f429920](https://github.com/SecretFoundation/SecretWiki/commit/f429920ad78cd72985abfeff91c0d21ccdfb4816): Delete infrastructure.md","index":154,"timestampMs":1598836079000},{"description":"[ff7fba1](https://github.com/SecretFoundation/SecretWiki/commit/ff7fba1042b446ec43698e04389edb98bbd7a63b): Update sgx.md","index":155,"timestampMs":1598841108000},{"description":"[ff4b3f1](https://github.com/SecretFoundation/SecretWiki/commit/ff4b3f1f2a0bb77fc262ebcafb1b67b88ecb3988): updates","index":156,"timestampMs":1593613895000},{"description":"[#1](https://github.com/SecretFoundation/SecretWiki/pull/1): Bump lodash from 4.17.15 to 4.17.19","index":157,"timestampMs":1595303916000},{"description":"[#2](https://github.com/SecretFoundation/SecretWiki/pull/2): Update Wiki Structure","index":158,"timestampMs":1595463452000},{"description":"[#3](https://github.com/SecretFoundation/SecretWiki/pull/3): Bump elliptic from 6.5.2 to 6.5.3","index":159,"timestampMs":1596340266000},{"description":"[#4](https://github.com/SecretFoundation/SecretWiki/pull/4): Bump prismjs from 1.20.0 to 1.21.0","index":160,"timestampMs":1596846530000},{"description":"[#5](https://github.com/SecretFoundation/SecretWiki/pull/5): Added link to the Working Document for SGX support","index":161,"timestampMs":1598840801000},{"description":"[#6](https://github.com/SecretFoundation/SecretWiki/pull/6): The dusky","index":162,"timestampMs":1599013086000},{"description":"[#7](https://github.com/SecretFoundation/SecretWiki/pull/7): Psychz Updates to the SGX.md page","index":163,"timestampMs":1599616004000},{"description":"[SecretFoundation/SecretWiki](https://github.com/SecretFoundation/SecretWiki)","index":164,"timestampMs":1591994817000},{"description":"github/[@dependabot](https://github.com/apps/dependabot)","index":165,"timestampMs":null},{"description":"github/[@jlwaugh](https://github.com/jlwaugh)","index":166,"timestampMs":null},{"description":"github/[@lauraweindorf](https://github.com/lauraweindorf)","index":167,"timestampMs":null},{"description":"github/[@mohammedpatla](https://github.com/mohammedpatla)","index":168,"timestampMs":null},{"description":"github/[@moonstash](https://github.com/moonstash)","index":169,"timestampMs":null},{"description":"github/[@the-dusky](https://github.com/the-dusky)","index":170,"timestampMs":null},{"description":"github/[@torsecret](https://github.com/torsecret)","index":171,"timestampMs":null}],"sortedNodeAddresses":[["sourcecred","git","COMMIT","010d4eba895899d30237260fa8bcd6475f2b898d"],["sourcecred","git","COMMIT","04ee7fd4259e25e80646c40773bed2fe55ac1316"],["sourcecred","git","COMMIT","07bc800b1593935d5762dd5d489b2c30cd65023e"],["sourcecred","git","COMMIT","09b8b5d757916d4fb73d2da9c7cb4e019258056d"],["sourcecred","git","COMMIT","0e96bbf496973694a71849f16e6629ec799073fe"],["sourcecred","git","COMMIT","14abd3cba611749f7caf4ce18e43f22d6bb43a85"],["sourcecred","git","COMMIT","1770c2b8324ce83a3771c4644ee21c17f53cdab1"],["sourcecred","git","COMMIT","1e9b855b2b5413e89aafb02a7c5d87dd7a912d62"],["sourcecred","git","COMMIT","1fd8dcb165322e5816e2e5cc5baca41a1c797f25"],["sourcecred","git","COMMIT","2226987104b3bf3b090a1e5436b00074dee9d60c"],["sourcecred","git","COMMIT","2494bb4f2f2398cbfba70ded6fcf71eac036c714"],["sourcecred","git","COMMIT","26bb2bca2de1a739fcbb39a9339066cbe2084fcf"],["sourcecred","git","COMMIT","315f57ef13b358fca24bbfaebe50ff825c9f09ce"],["sourcecred","git","COMMIT","31ea5a10dd2cc0731d3a64e75547dfb036bb1d79"],["sourcecred","git","COMMIT","33aa8c92cfdbc80a756ac9d371ce7cc1785bc224"],["sourcecred","git","COMMIT","35360b654a1b81fdfd45245a74c923c81b4696c0"],["sourcecred","git","COMMIT","3810ef1cf34a101e170328b09d4599ef0b21d06c"],["sourcecred","git","COMMIT","3f61905b71145f54a8a2629304e6a415816a62b1"],["sourcecred","git","COMMIT","41d0fe73606db574a5ff4046906881f20f9c2297"],["sourcecred","git","COMMIT","4234584956e1e4552b36fed7e7355a43c03bdfae"],["sourcecred","git","COMMIT","49990fea127701776947930a7534b3adae0fc8e6"],["sourcecred","git","COMMIT","4cfdd04dcae7b1a4e0056aba0debaed808600ab8"],["sourcecred","git","COMMIT","506d211e7ab9e784e8523e8910754672b800eeb8"],["sourcecred","git","COMMIT","515302fe4bfc3744114bcbbb3ec03f344d243455"],["sourcecred","git","COMMIT","5536a46da6a8e68aeefe092492e62ce5765e4289"],["sourcecred","git","COMMIT","5d371e5b5a749d0fbd8e7948fbef392a2e7ad3d0"],["sourcecred","git","COMMIT","5d75af63f97a9624095a2a508d152d3bd9f29487"],["sourcecred","git","COMMIT","61085cb6508f7865662f3acc380e9d8d4f9ea7df"],["sourcecred","git","COMMIT","61624997ef8d100bab58cbc2df0e1bbaa5a78a02"],["sourcecred","git","COMMIT","64356742edde96eba8f4cb6a64c6946ba36b6710"],["sourcecred","git","COMMIT","6452b1c9cd132fe5b60c5bd9a6d8fe81bf075808"],["sourcecred","git","COMMIT","658f2b14da24aa2bfa903e10d8ce2c8dee5f182b"],["sourcecred","git","COMMIT","6c2b073c22327ffdf1f5f56a98af73ae46f71d43"],["sourcecred","git","COMMIT","6d4e30253352066392189d306a6be08accaff741"],["sourcecred","git","COMMIT","6fccd263b8c359ab64f343ca26a605be44c90c3a"],["sourcecred","git","COMMIT","70729e36871038a2e320e5bac0287c3c74d31887"],["sourcecred","git","COMMIT","73b70ebba6f8221868299832270149b27894d882"],["sourcecred","git","COMMIT","7599b9edeedf8697abb08cb1c4c7a4edfd5a194e"],["sourcecred","git","COMMIT","78689d4c787584414da761c636ae875940001777"],["sourcecred","git","COMMIT","78ae661c1ff42ae9da06e8d5cb10cff38d7b360c"],["sourcecred","git","COMMIT","7bcf9e62568006b9134f94cbb6abaaed72e825ed"],["sourcecred","git","COMMIT","818068a96c50af5c4a77594f00c01bb41600e3a8"],["sourcecred","git","COMMIT","8307316dbda9a4a276ab8bcd3476ad9762d50b07"],["sourcecred","git","COMMIT","8bcc016d2805f490d26f02c36d35f6fb6f377101"],["sourcecred","git","COMMIT","8c9b25da1ab6f8c88ccc8a3c71afeeb0f8cc5ebd"],["sourcecred","git","COMMIT","8d396c93ad4980639791a975be00c17eb2ba6845"],["sourcecred","git","COMMIT","8e8335e405565bcec9b448efcf213972973a6f2c"],["sourcecred","git","COMMIT","90322069298ecdd16daccc1e1b5d2b6584c85bf5"],["sourcecred","git","COMMIT","91adee9b098a867c1b679bb3e1baa091689f07aa"],["sourcecred","git","COMMIT","9cc260cef875658651329ec1710fc0697ff326d9"],["sourcecred","git","COMMIT","a796f711026a75c3a337ae8696fe3ee61ce47e38"],["sourcecred","git","COMMIT","af17f57c130893d0d38a7cffcee01213220babbb"],["sourcecred","git","COMMIT","b23fd11910d288b6153965cb4576351c880625f4"],["sourcecred","git","COMMIT","b32da486f7f0a0fc59c68962488044b0faa6fb40"],["sourcecred","git","COMMIT","b49a718d2ef70787dd55b38ee1e171cff94991d6"],["sourcecred","git","COMMIT","b51fadd921b8724a490c9d57af245e4ec5097c37"],["sourcecred","git","COMMIT","b6a2e669ea25b39301016a67e36fac5801e8823b"],["sourcecred","git","COMMIT","baad65ea06a6051ab0903cf77132351a1ca7f093"],["sourcecred","git","COMMIT","c6be690fbefc8925487af51463d6d88a90a401e6"],["sourcecred","git","COMMIT","cb66b458557d8a4b6ddbb239154e6931a105e83a"],["sourcecred","git","COMMIT","d25ed2445cd3efb000cbb22a4af9b0f45b2ca492"],["sourcecred","git","COMMIT","d51e2f72193cd399ac28e2d2b93894b6d786f793"],["sourcecred","git","COMMIT","d6fb6c18488e06c2559808cdc7944a0d9301cf39"],["sourcecred","git","COMMIT","d856e7f3c6fc0e9bdd9524ac29cc7ea70f9779ad"],["sourcecred","git","COMMIT","dfd6e03890b47daf2e8b1ed4503672349b009555"],["sourcecred","git","COMMIT","e21df9693e1b42b79d11b3c4e0dbc25d73a16844"],["sourcecred","git","COMMIT","e2c97680da66b4a5996d52611123cb7f6950323b"],["sourcecred","git","COMMIT","e3d8c3e59130a429be0505ece6aa1bbe99847825"],["sourcecred","git","COMMIT","e8598a0daf531fef788d5491e19281134bca21c0"],["sourcecred","git","COMMIT","ea8ec8f142f93c681d3178dc82f5c30d8b738692"],["sourcecred","git","COMMIT","eaafe43d88082a13aac87621d6c5b62099841304"],["sourcecred","git","COMMIT","ecf731d2b5479a7cb82eded38efccac4d0850b51"],["sourcecred","git","COMMIT","ed3d84dafd7e93410ca8b248d17aa34a19097c00"],["sourcecred","git","COMMIT","f429920ad78cd72985abfeff91c0d21ccdfb4816"],["sourcecred","git","COMMIT","ff4b3f1f2a0bb77fc262ebcafb1b67b88ecb3988"],["sourcecred","git","COMMIT","ff7fba1042b446ec43698e04389edb98bbd7a63b"],["sourcecred","github","COMMENT","PULL","SecretFoundation","SecretWiki","5","683518918"],["sourcecred","github","COMMENT","PULL","SecretFoundation","SecretWiki","5","683523498"],["sourcecred","github","COMMENT","PULL","SecretFoundation","SecretWiki","6","685292773"],["sourcecred","github","COMMENT","PULL","SecretFoundation","SecretWiki","6","689233361"],["sourcecred","github","COMMENT","PULL","SecretFoundation","SecretWiki","6","691184387"],["sourcecred","github","COMMIT","MDY6Q29tbWl0MjcxODg3MzcwOjA0ZWU3ZmQ0MjU5ZTI1ZTgwNjQ2YzQwNzczYmVkMmZlNTVhYzEzMTY="],["sourcecred","github","COMMIT","MDY6Q29tbWl0MjcxODg3MzcwOjA3YmM4MDBiMTU5MzkzNWQ1NzYyZGQ1ZDQ4OWIyYzMwY2Q2NTAyM2U="],["sourcecred","github","COMMIT","MDY6Q29tbWl0MjcxODg3MzcwOjA5YjhiNWQ3NTc5MTZkNGZiNzNkMmRhOWM3Y2I0ZTAxOTI1ODA1NmQ="],["sourcecred","github","COMMIT","MDY6Q29tbWl0MjcxODg3MzcwOjAxMGQ0ZWJhODk1ODk5ZDMwMjM3MjYwZmE4YmNkNjQ3NWYyYjg5OGQ="],["sourcecred","github","COMMIT","MDY6Q29tbWl0MjcxODg3MzcwOjBlOTZiYmY0OTY5NzM2OTRhNzE4NDlmMTZlNjYyOWVjNzk5MDczZmU="],["sourcecred","github","COMMIT","MDY6Q29tbWl0MjcxODg3MzcwOjE0YWJkM2NiYTYxMTc0OWY3Y2FmNGNlMThlNDNmMjJkNmJiNDNhODU="],["sourcecred","github","COMMIT","MDY6Q29tbWl0MjcxODg3MzcwOjE3NzBjMmI4MzI0Y2U4M2EzNzcxYzQ2NDRlZTIxYzE3ZjUzY2RhYjE="],["sourcecred","github","COMMIT","MDY6Q29tbWl0MjcxODg3MzcwOjFlOWI4NTViMmI1NDEzZTg5YWFmYjAyYTdjNWQ4N2RkN2E5MTJkNjI="],["sourcecred","github","COMMIT","MDY6Q29tbWl0MjcxODg3MzcwOjFmZDhkY2IxNjUzMjJlNTgxNmUyZTVjYzViYWNhNDFhMWM3OTdmMjU="],["sourcecred","github","COMMIT","MDY6Q29tbWl0MjcxODg3MzcwOjI0OTRiYjRmMmYyMzk4Y2JmYmE3MGRlZDZmY2Y3MWVhYzAzNmM3MTQ="],["sourcecred","github","COMMIT","MDY6Q29tbWl0MjcxODg3MzcwOjI2YmIyYmNhMmRlMWE3MzlmY2JiMzlhOTMzOTA2NmNiZTIwODRmY2Y="],["sourcecred","github","COMMIT","MDY6Q29tbWl0MjcxODg3MzcwOjIyMjY5ODcxMDRiM2JmM2IwOTBhMWU1NDM2YjAwMDc0ZGVlOWQ2MGM="],["sourcecred","github","COMMIT","MDY6Q29tbWl0MjcxODg3MzcwOjM1MzYwYjY1NGExYjgxZmRmZDQ1MjQ1YTc0YzkyM2M4MWI0Njk2YzA="],["sourcecred","github","COMMIT","MDY6Q29tbWl0MjcxODg3MzcwOjM4MTBlZjFjZjM0YTEwMWUxNzAzMjhiMDlkNDU5OWVmMGIyMWQwNmM="],["sourcecred","github","COMMIT","MDY6Q29tbWl0MjcxODg3MzcwOjMxNWY1N2VmMTNiMzU4ZmNhMjRiYmZhZWJlNTBmZjgyNWM5ZjA5Y2U="],["sourcecred","github","COMMIT","MDY6Q29tbWl0MjcxODg3MzcwOjMxZWE1YTEwZGQyY2MwNzMxZDNhNjRlNzU1NDdkZmIwMzZiYjFkNzk="],["sourcecred","github","COMMIT","MDY6Q29tbWl0MjcxODg3MzcwOjMzYWE4YzkyY2ZkYmM4MGE3NTZhYzlkMzcxY2U3Y2MxNzg1YmMyMjQ="],["sourcecred","github","COMMIT","MDY6Q29tbWl0MjcxODg3MzcwOjNmNjE5MDViNzExNDVmNTRhOGEyNjI5MzA0ZTZhNDE1ODE2YTYyYjE="],["sourcecred","github","COMMIT","MDY6Q29tbWl0MjcxODg3MzcwOjQ5OTkwZmVhMTI3NzAxNzc2OTQ3OTMwYTc1MzRiM2FkYWUwZmM4ZTY="],["sourcecred","github","COMMIT","MDY6Q29tbWl0MjcxODg3MzcwOjQxZDBmZTczNjA2ZGI1NzRhNWZmNDA0NjkwNjg4MWYyMGY5YzIyOTc="],["sourcecred","github","COMMIT","MDY6Q29tbWl0MjcxODg3MzcwOjQyMzQ1ODQ5NTZlMWU0NTUyYjM2ZmVkN2U3MzU1YTQzYzAzYmRmYWU="],["sourcecred","github","COMMIT","MDY6Q29tbWl0MjcxODg3MzcwOjRjZmRkMDRkY2FlN2IxYTRlMDA1NmFiYTBkZWJhZWQ4MDg2MDBhYjg="],["sourcecred","github","COMMIT","MDY6Q29tbWl0MjcxODg3MzcwOjU1MzZhNDZkYTZhOGU2OGFlZWZlMDkyNDkyZTYyY2U1NzY1ZTQyODk="],["sourcecred","github","COMMIT","MDY6Q29tbWl0MjcxODg3MzcwOjUwNmQyMTFlN2FiOWU3ODRlODUyM2U4OTEwNzU0NjcyYjgwMGVlYjg="],["sourcecred","github","COMMIT","MDY6Q29tbWl0MjcxODg3MzcwOjUxNTMwMmZlNGJmYzM3NDQxMTRiY2JiYjNlYzAzZjM0NGQyNDM0NTU="],["sourcecred","github","COMMIT","MDY6Q29tbWl0MjcxODg3MzcwOjVkMzcxZTViNWE3NDlkMGZiZDhlNzk0OGZiZWYzOTJhMmU3YWQzZDA="],["sourcecred","github","COMMIT","MDY6Q29tbWl0MjcxODg3MzcwOjVkNzVhZjYzZjk3YTk2MjQwOTVhMmE1MDhkMTUyZDNiZDlmMjk0ODc="],["sourcecred","github","COMMIT","MDY6Q29tbWl0MjcxODg3MzcwOjY0MzU2NzQyZWRkZTk2ZWJhOGY0Y2I2YTY0YzY5NDZiYTM2YjY3MTA="],["sourcecred","github","COMMIT","MDY6Q29tbWl0MjcxODg3MzcwOjY0NTJiMWM5Y2QxMzJmZTViNjBjNWJkOWE2ZDhmZTgxYmYwNzU4MDg="],["sourcecred","github","COMMIT","MDY6Q29tbWl0MjcxODg3MzcwOjY1OGYyYjE0ZGEyNGFhMmJmYTkwM2UxMGQ4Y2UyYzhkZWU1ZjE4MmI="],["sourcecred","github","COMMIT","MDY6Q29tbWl0MjcxODg3MzcwOjYxMDg1Y2I2NTA4Zjc4NjU2NjJmM2FjYzM4MGU5ZDhkNGY5ZWE3ZGY="],["sourcecred","github","COMMIT","MDY6Q29tbWl0MjcxODg3MzcwOjYxNjI0OTk3ZWY4ZDEwMGJhYjU4Y2JjMmRmMGUxYmJhYTVhNzhhMDI="],["sourcecred","github","COMMIT","MDY6Q29tbWl0MjcxODg3MzcwOjZjMmIwNzNjMjIzMjdmZmRmMWY1ZjU2YTk4YWY3M2FlNDZmNzFkNDM="],["sourcecred","github","COMMIT","MDY6Q29tbWl0MjcxODg3MzcwOjZkNGUzMDI1MzM1MjA2NjM5MjE4OWQzMDZhNmJlMDhhY2NhZmY3NDE="],["sourcecred","github","COMMIT","MDY6Q29tbWl0MjcxODg3MzcwOjZmY2NkMjYzYjhjMzU5YWI2NGYzNDNjYTI2YTYwNWJlNDRjOTBjM2E="],["sourcecred","github","COMMIT","MDY6Q29tbWl0MjcxODg3MzcwOjc1OTliOWVkZWVkZjg2OTdhYmIwOGNiMWM0YzdhNGVkZmQ1YTE5NGU="],["sourcecred","github","COMMIT","MDY6Q29tbWl0MjcxODg3MzcwOjc4Njg5ZDRjNzg3NTg0NDE0ZGE3NjFjNjM2YWU4NzU5NDAwMDE3Nzc="],["sourcecred","github","COMMIT","MDY6Q29tbWl0MjcxODg3MzcwOjc4YWU2NjFjMWZmNDJhZTlkYTA2ZThkNWNiMTBjZmYzOGQ3YjM2MGM="],["sourcecred","github","COMMIT","MDY6Q29tbWl0MjcxODg3MzcwOjcwNzI5ZTM2ODcxMDM4YTJlMzIwZTViYWMwMjg3YzNjNzRkMzE4ODc="],["sourcecred","github","COMMIT","MDY6Q29tbWl0MjcxODg3MzcwOjczYjcwZWJiYTZmODIyMTg2ODI5OTgzMjI3MDE0OWIyNzg5NGQ4ODI="],["sourcecred","github","COMMIT","MDY6Q29tbWl0MjcxODg3MzcwOjdiY2Y5ZTYyNTY4MDA2YjkxMzRmOTRjYmI2YWJhYWVkNzJlODI1ZWQ="],["sourcecred","github","COMMIT","MDY6Q29tbWl0MjcxODg3MzcwOjgxODA2OGE5NmM1MGFmNWM0YTc3NTk0ZjAwYzAxYmI0MTYwMGUzYTg="],["sourcecred","github","COMMIT","MDY6Q29tbWl0MjcxODg3MzcwOjgzMDczMTZkYmRhOWE0YTI3NmFiOGJjZDM0NzZhZDk3NjJkNTBiMDc="],["sourcecred","github","COMMIT","MDY6Q29tbWl0MjcxODg3MzcwOjhiY2MwMTZkMjgwNWY0OTBkMjZmMDJjMzZkMzVmNmZiNmYzNzcxMDE="],["sourcecred","github","COMMIT","MDY6Q29tbWl0MjcxODg3MzcwOjhjOWIyNWRhMWFiNmY4Yzg4Y2NjOGEzYzcxYWZlZWIwZjhjYzVlYmQ="],["sourcecred","github","COMMIT","MDY6Q29tbWl0MjcxODg3MzcwOjhkMzk2YzkzYWQ0OTgwNjM5NzkxYTk3NWJlMDBjMTdlYjJiYTY4NDU="],["sourcecred","github","COMMIT","MDY6Q29tbWl0MjcxODg3MzcwOjhlODMzNWU0MDU1NjViY2VjOWI0NDhlZmNmMjEzOTcyOTczYTZmMmM="],["sourcecred","github","COMMIT","MDY6Q29tbWl0MjcxODg3MzcwOjkwMzIyMDY5Mjk4ZWNkZDE2ZGFjY2MxZTFiNWQyYjY1ODRjODViZjU="],["sourcecred","github","COMMIT","MDY6Q29tbWl0MjcxODg3MzcwOjkxYWRlZTliMDk4YTg2N2MxYjY3OWJiM2UxYmFhMDkxNjg5ZjA3YWE="],["sourcecred","github","COMMIT","MDY6Q29tbWl0MjcxODg3MzcwOjljYzI2MGNlZjg3NTY1ODY1MTMyOWVjMTcxMGZjMDY5N2ZmMzI2ZDk="],["sourcecred","github","COMMIT","MDY6Q29tbWl0MjcxODg3MzcwOmE3OTZmNzExMDI2YTc1YzNhMzM3YWU4Njk2ZmUzZWU2MWNlNDdlMzg="],["sourcecred","github","COMMIT","MDY6Q29tbWl0MjcxODg3MzcwOmFmMTdmNTdjMTMwODkzZDBkMzhhN2NmZmNlZTAxMjEzMjIwYmFiYmI="],["sourcecred","github","COMMIT","MDY6Q29tbWl0MjcxODg3MzcwOmI0OWE3MThkMmVmNzA3ODdkZDU1YjM4ZWUxZTE3MWNmZjk0OTkxZDY="],["sourcecred","github","COMMIT","MDY6Q29tbWl0MjcxODg3MzcwOmI1MWZhZGQ5MjFiODcyNGE0OTBjOWQ1N2FmMjQ1ZTRlYzUwOTdjMzc="],["sourcecred","github","COMMIT","MDY6Q29tbWl0MjcxODg3MzcwOmI2YTJlNjY5ZWEyNWIzOTMwMTAxNmE2N2UzNmZhYzU4MDFlODgyM2I="],["sourcecred","github","COMMIT","MDY6Q29tbWl0MjcxODg3MzcwOmIyM2ZkMTE5MTBkMjg4YjYxNTM5NjVjYjQ1NzYzNTFjODgwNjI1ZjQ="],["sourcecred","github","COMMIT","MDY6Q29tbWl0MjcxODg3MzcwOmIzMmRhNDg2ZjdmMGEwZmM1OWM2ODk2MjQ4ODA0NGIwZmFhNmZiNDA="],["sourcecred","github","COMMIT","MDY6Q29tbWl0MjcxODg3MzcwOmJhYWQ2NWVhMDZhNjA1MWFiMDkwM2NmNzcxMzIzNTFhMWNhN2YwOTM="],["sourcecred","github","COMMIT","MDY6Q29tbWl0MjcxODg3MzcwOmM2YmU2OTBmYmVmYzg5MjU0ODdhZjUxNDYzZDZkODhhOTBhNDAxZTY="],["sourcecred","github","COMMIT","MDY6Q29tbWl0MjcxODg3MzcwOmNiNjZiNDU4NTU3ZDhhNGI2ZGRiYjIzOTE1NGU2OTMxYTEwNWU4M2E="],["sourcecred","github","COMMIT","MDY6Q29tbWl0MjcxODg3MzcwOmQ1MWUyZjcyMTkzY2QzOTlhYzI4ZTJkMmI5Mzg5NGI2ZDc4NmY3OTM="],["sourcecred","github","COMMIT","MDY6Q29tbWl0MjcxODg3MzcwOmQ2ZmI2YzE4NDg4ZTA2YzI1NTk4MDhjZGM3OTQ0YTBkOTMwMWNmMzk="],["sourcecred","github","COMMIT","MDY6Q29tbWl0MjcxODg3MzcwOmQ4NTZlN2YzYzZmYzBlOWJkZDk1MjRhYzI5Y2M3ZWE3MGY5Nzc5YWQ="],["sourcecred","github","COMMIT","MDY6Q29tbWl0MjcxODg3MzcwOmQyNWVkMjQ0NWNkM2VmYjAwMGNiYjIyYTRhZjliMGY0NWIyY2E0OTI="],["sourcecred","github","COMMIT","MDY6Q29tbWl0MjcxODg3MzcwOmRmZDZlMDM4OTBiNDdkYWYyZThiMWVkNDUwMzY3MjM0OWIwMDk1NTU="],["sourcecred","github","COMMIT","MDY6Q29tbWl0MjcxODg3MzcwOmU4NTk4YTBkYWY1MzFmZWY3ODhkNTQ5MWUxOTI4MTEzNGJjYTIxYzA="],["sourcecred","github","COMMIT","MDY6Q29tbWl0MjcxODg3MzcwOmUyMWRmOTY5M2UxYjQyYjc5ZDExYjNjNGUwZGJjMjVkNzNhMTY4NDQ="],["sourcecred","github","COMMIT","MDY6Q29tbWl0MjcxODg3MzcwOmUyYzk3NjgwZGE2NmI0YTU5OTZkNTI2MTExMjNjYjdmNjk1MDMyM2I="],["sourcecred","github","COMMIT","MDY6Q29tbWl0MjcxODg3MzcwOmUzZDhjM2U1OTEzMGE0MjliZTA1MDVlY2U2YWExYmJlOTk4NDc4MjU="],["sourcecred","github","COMMIT","MDY6Q29tbWl0MjcxODg3MzcwOmVhOGVjOGYxNDJmOTNjNjgxZDMxNzhkYzgyZjVjMzBkOGI3Mzg2OTI="],["sourcecred","github","COMMIT","MDY6Q29tbWl0MjcxODg3MzcwOmVhYWZlNDNkODgwODJhMTNhYWM4NzYyMWQ2YzViNjIwOTk4NDEzMDQ="],["sourcecred","github","COMMIT","MDY6Q29tbWl0MjcxODg3MzcwOmVjZjczMWQyYjU0NzlhN2NiODJlZGVkMzhlZmNjYWM0ZDA4NTBiNTE="],["sourcecred","github","COMMIT","MDY6Q29tbWl0MjcxODg3MzcwOmVkM2Q4NGRhZmQ3ZTkzNDEwY2E4YjI0OGQxN2FhMzRhMTkwOTdjMDA="],["sourcecred","github","COMMIT","MDY6Q29tbWl0MjcxODg3MzcwOmY0Mjk5MjBhZDc4Y2Q3Mjk4NWFiZmVmZjkxYzBkMjFjY2RmYjQ4MTY="],["sourcecred","github","COMMIT","MDY6Q29tbWl0MjcxODg3MzcwOmZmN2ZiYTEwNDJiNDQ2ZWM0MzY5OGUwNDM4OWVkYjk4YmJkN2E2M2I="],["sourcecred","github","COMMIT","MDY6Q29tbWl0MjcxODg3MzcwOmZmNGIzZjFmMmEwYmI3N2ZjMjYyZWJjYWZiMWI2N2I4OGVjYjM5ODg="],["sourcecred","github","PULL","SecretFoundation","SecretWiki","1"],["sourcecred","github","PULL","SecretFoundation","SecretWiki","2"],["sourcecred","github","PULL","SecretFoundation","SecretWiki","3"],["sourcecred","github","PULL","SecretFoundation","SecretWiki","4"],["sourcecred","github","PULL","SecretFoundation","SecretWiki","5"],["sourcecred","github","PULL","SecretFoundation","SecretWiki","6"],["sourcecred","github","PULL","SecretFoundation","SecretWiki","7"],["sourcecred","github","REPO","SecretFoundation","SecretWiki"],["sourcecred","github","USERLIKE","BOT","dependabot"],["sourcecred","github","USERLIKE","USER","jlwaugh"],["sourcecred","github","USERLIKE","USER","lauraweindorf"],["sourcecred","github","USERLIKE","USER","mohammedpatla"],["sourcecred","github","USERLIKE","USER","moonstash"],["sourcecred","github","USERLIKE","USER","the-dusky"],["sourcecred","github","USERLIKE","USER","torsecret"]]}],"weightsJSON":[{"type":"sourcecred/weights","version":"0.2.0"},{"edgeWeights":{"E\u0000sourcecred\u0000github\u0000AUTHORS\u0000":{"backwards":1,"forwards":0.5},"E\u0000sourcecred\u0000github\u0000CORRESPONDS_TO_COMMIT_TYPE\u0000":{"backwards":1,"forwards":1},"E\u0000sourcecred\u0000github\u0000HAS_PARENT\u0000":{"backwards":0.25,"forwards":1},"E\u0000sourcecred\u0000github\u0000MERGED_AS\u0000":{"backwards":1,"forwards":0.5},"E\u0000sourcecred\u0000github\u0000REACTS\u0000HEART\u0000":{"backwards":0,"forwards":2},"E\u0000sourcecred\u0000github\u0000REACTS\u0000HOORAY\u0000":{"backwards":0,"forwards":4},"E\u0000sourcecred\u0000github\u0000REACTS\u0000ROCKET\u0000":{"backwards":0,"forwards":1},"E\u0000sourcecred\u0000github\u0000REACTS\u0000THUMBS_UP\u0000":{"backwards":0,"forwards":1},"E\u0000sourcecred\u0000github\u0000REFERENCES\u0000":{"backwards":0,"forwards":1}},"nodeWeights":{"N\u0000sourcecred\u0000github\u0000COMMENT\u0000":0,"N\u0000sourcecred\u0000github\u0000COMMIT\u0000":0,"N\u0000sourcecred\u0000github\u0000ISSUE\u0000":0,"N\u0000sourcecred\u0000github\u0000PULL\u0000":4,"N\u0000sourcecred\u0000github\u0000PULL\u0000SecretFoundation\u0000SecretWiki\u00006\u0000":0,"N\u0000sourcecred\u0000github\u0000REPO\u0000":0,"N\u0000sourcecred\u0000github\u0000REVIEW\u0000":1,"N\u0000sourcecred\u0000github\u0000USERLIKE\u0000BOT\u0000":0,"N\u0000sourcecred\u0000github\u0000USERLIKE\u0000USER\u0000":0}}]}]